[
  {
    "CANAL_ID": "UCMP3ETiqEPs0RMjxH57O5DQ",
    "ANO": 2026,
    "MES": 5,
    "DIA": "2026-05-16",
    "INSCRITOS": "8840"
  },
  {
    "CANAL_ID": "UCwONybZQdULFV_ts2911Rqg",
    "ANO": 2026,
    "MES": 5,
    "DIA": "2026-05-16",
    "INSCRITOS": "816000"
  },
  {
    "CANAL_ID": "UC74FvQ6GtdwRmENGymLjqNA",
    "ANO": 2026,
    "MES": 5,
    "DIA": "2026-05-16",
    "INSCRITOS": "73800"
  },
  {
    "CANAL_ID": "UCAbPPg9IVIjzPBAE7uGgd-g",
    "ANO": 2026,
    "MES": 5,
    "DIA": "2026-05-16",
    "INSCRITOS": "67500"
  },
  {
    "CANAL_ID": "UC7k3dDEfclcB07Deoy41D6g",
    "ANO": 2026,
    "MES": 5,
    "DIA": "2026-05-16",
    "INSCRITOS": "61700"
  },
  {
    "CANAL_ID": "UCWDeEIDAIi_oYKDiqwfGyRg",
    "ANO": 2026,
    "MES": 5,
    "DIA": "2026-05-16",
    "INSCRITOS": "518000"
  },
  {
    "CANAL_ID": "UCSXdP8V4jRaw-8YMTpa6glw",
    "ANO": 2026,
    "MES": 5,
    "DIA": "2026-05-16",
    "INSCRITOS": "349000"
  },
  {
    "CANAL_ID": "UCMP3ETiqEPs0RMjxH57O5DQ",
    "ANO": 2026,
    "MES": 4,
    "DIA": "2026-04-30",
    "INSCRITOS": "8730"
  },
  {
    "CANAL_ID": "UCwONybZQdULFV_ts2911Rqg",
    "ANO": 2026,
    "MES": 4,
    "DIA": "2026-04-30",
    "INSCRITOS": "814000"
  },
  {
    "CANAL_ID": "UC74FvQ6GtdwRmENGymLjqNA",
    "ANO": 2026,
    "MES": 4,
    "DIA": "2026-04-30",
    "INSCRITOS": "73800"
  },
  {
    "CANAL_ID": "UCAbPPg9IVIjzPBAE7uGgd-g",
    "ANO": 2026,
    "MES": 4,
    "DIA": "2026-04-30",
    "INSCRITOS": "67400"
  },
  {
    "CANAL_ID": "UC7k3dDEfclcB07Deoy41D6g",
    "ANO": 2026,
    "MES": 4,
    "DIA": "2026-04-30",
    "INSCRITOS": "61400"
  },
  {
    "CANAL_ID": "UCWDeEIDAIi_oYKDiqwfGyRg",
    "ANO": 2026,
    "MES": 4,
    "DIA": "2026-04-30",
    "INSCRITOS": "518000"
  },
  {
    "CANAL_ID": "UCSXdP8V4jRaw-8YMTpa6glw",
    "ANO": 2026,
    "MES": 4,
    "DIA": "2026-04-30",
    "INSCRITOS": "349000"
  },
  {
    "CANAL_ID": "UCMP3ETiqEPs0RMjxH57O5DQ",
    "ANO": 2026,
    "MES": 3,
    "DIA": "2026-03-31",
    "INSCRITOS": "8420"
  },
  {
    "CANAL_ID": "UCwONybZQdULFV_ts2911Rqg",
    "ANO": 2026,
    "MES": 3,
    "DIA": "2026-03-31",
    "INSCRITOS": "805000"
  },
  {
    "CANAL_ID": "UC74FvQ6GtdwRmENGymLjqNA",
    "ANO": 2026,
    "MES": 3,
    "DIA": "2026-03-31",
    "INSCRITOS": "73900"
  },
  {
    "CANAL_ID": "UCAbPPg9IVIjzPBAE7uGgd-g",
    "ANO": 2026,
    "MES": 3,
    "DIA": "2026-03-31",
    "INSCRITOS": "67200"
  },
  {
    "CANAL_ID": "UC7k3dDEfclcB07Deoy41D6g",
    "ANO": 2026,
    "MES": 3,
    "DIA": "2026-03-31",
    "INSCRITOS": "56800"
  },
  {
    "CANAL_ID": "UCWDeEIDAIi_oYKDiqwfGyRg",
    "ANO": 2026,
    "MES": 3,
    "DIA": "2026-03-30",
    "INSCRITOS": "514000"
  },
  {
    "CANAL_ID": "UCSXdP8V4jRaw-8YMTpa6glw",
    "ANO": 2026,
    "MES": 3,
    "DIA": "2026-03-31",
    "INSCRITOS": "344000"
  },
  {
    "CANAL_ID": "UCMP3ETiqEPs0RMjxH57O5DQ",
    "ANO": 2026,
    "MES": 2,
    "DIA": "2026-02-28",
    "INSCRITOS": "8220"
  },
  {
    "CANAL_ID": "UCwONybZQdULFV_ts2911Rqg",
    "ANO": 2026,
    "MES": 2,
    "DIA": "2026-02-28",
    "INSCRITOS": "796000"
  },
  {
    "CANAL_ID": "UC74FvQ6GtdwRmENGymLjqNA",
    "ANO": 2026,
    "MES": 2,
    "DIA": "2026-02-28",
    "INSCRITOS": "73900"
  },
  {
    "CANAL_ID": "UCAbPPg9IVIjzPBAE7uGgd-g",
    "ANO": 2026,
    "MES": 2,
    "DIA": "2026-02-28",
    "INSCRITOS": "67000"
  },
  {
    "CANAL_ID": "UC7k3dDEfclcB07Deoy41D6g",
    "ANO": 2026,
    "MES": 2,
    "DIA": "2026-02-28",
    "INSCRITOS": "51300"
  },
  {
    "CANAL_ID": "UCWDeEIDAIi_oYKDiqwfGyRg",
    "ANO": 2026,
    "MES": 2,
    "DIA": "2026-02-16",
    "INSCRITOS": "510000"
  },
  {
    "CANAL_ID": "UCSXdP8V4jRaw-8YMTpa6glw",
    "ANO": 2026,
    "MES": 2,
    "DIA": "2026-02-28",
    "INSCRITOS": "339000"
  },
  {
    "CANAL_ID": "UCMP3ETiqEPs0RMjxH57O5DQ",
    "ANO": 2026,
    "MES": 1,
    "DIA": "2026-01-31",
    "INSCRITOS": "7950"
  },
  {
    "CANAL_ID": "UCwONybZQdULFV_ts2911Rqg",
    "ANO": 2026,
    "MES": 1,
    "DIA": "2026-01-31",
    "INSCRITOS": "791000"
  },
  {
    "CANAL_ID": "UC74FvQ6GtdwRmENGymLjqNA",
    "ANO": 2026,
    "MES": 1,
    "DIA": "2026-01-31",
    "INSCRITOS": "74000"
  },
  {
    "CANAL_ID": "UCAbPPg9IVIjzPBAE7uGgd-g",
    "ANO": 2026,
    "MES": 1,
    "DIA": "2026-01-31",
    "INSCRITOS": "66300"
  },
  {
    "CANAL_ID": "UCWDeEIDAIi_oYKDiqwfGyRg",
    "ANO": 2026,
    "MES": 1,
    "DIA": "2026-01-23",
    "INSCRITOS": "509000"
  },
  {
    "CANAL_ID": "UC7k3dDEfclcB07Deoy41D6g",
    "ANO": 2026,
    "MES": 1,
    "DIA": "2026-01-31",
    "INSCRITOS": "47000"
  },
  {
    "CANAL_ID": "UCSXdP8V4jRaw-8YMTpa6glw",
    "ANO": 2026,
    "MES": 1,
    "DIA": "2026-01-31",
    "INSCRITOS": "334000"
  },
  {
    "CANAL_ID": "UCwONybZQdULFV_ts2911Rqg",
    "ANO": 2025,
    "MES": 12,
    "DIA": "2025-12-31",
    "INSCRITOS": "779000"
  },
  {
    "CANAL_ID": "UCMP3ETiqEPs0RMjxH57O5DQ",
    "ANO": 2025,
    "MES": 12,
    "DIA": "2025-12-31",
    "INSCRITOS": "7650"
  },
  {
    "CANAL_ID": "UC74FvQ6GtdwRmENGymLjqNA",
    "ANO": 2025,
    "MES": 12,
    "DIA": "2025-12-31",
    "INSCRITOS": "74100"
  },
  {
    "CANAL_ID": "UCAbPPg9IVIjzPBAE7uGgd-g",
    "ANO": 2025,
    "MES": 12,
    "DIA": "2025-12-31",
    "INSCRITOS": "66200"
  },
  {
    "CANAL_ID": "UCWDeEIDAIi_oYKDiqwfGyRg",
    "ANO": 2025,
    "MES": 12,
    "DIA": "2025-12-29",
    "INSCRITOS": "505000"
  },
  {
    "CANAL_ID": "UC7k3dDEfclcB07Deoy41D6g",
    "ANO": 2025,
    "MES": 12,
    "DIA": "2025-12-31",
    "INSCRITOS": "43400"
  },
  {
    "CANAL_ID": "UCSXdP8V4jRaw-8YMTpa6glw",
    "ANO": 2025,
    "MES": 12,
    "DIA": "2025-12-31",
    "INSCRITOS": "329000"
  },
  {
    "CANAL_ID": "UCwONybZQdULFV_ts2911Rqg",
    "ANO": 2025,
    "MES": 11,
    "DIA": "2025-11-28",
    "INSCRITOS": "766000"
  },
  {
    "CANAL_ID": "UC74FvQ6GtdwRmENGymLjqNA",
    "ANO": 2025,
    "MES": 11,
    "DIA": "2025-11-28",
    "INSCRITOS": "74200"
  },
  {
    "CANAL_ID": "UCMP3ETiqEPs0RMjxH57O5DQ",
    "ANO": 2025,
    "MES": 11,
    "DIA": "2025-11-28",
    "INSCRITOS": "6930"
  },
  {
    "CANAL_ID": "UCAbPPg9IVIjzPBAE7uGgd-g",
    "ANO": 2025,
    "MES": 11,
    "DIA": "2025-11-28",
    "INSCRITOS": "66200"
  },
  {
    "CANAL_ID": "UCWDeEIDAIi_oYKDiqwfGyRg",
    "ANO": 2025,
    "MES": 11,
    "DIA": "2025-11-27",
    "INSCRITOS": "504000"
  },
  {
    "CANAL_ID": "UC7k3dDEfclcB07Deoy41D6g",
    "ANO": 2025,
    "MES": 11,
    "DIA": "2025-11-28",
    "INSCRITOS": "41400"
  },
  {
    "CANAL_ID": "UCSXdP8V4jRaw-8YMTpa6glw",
    "ANO": 2025,
    "MES": 11,
    "DIA": "2025-11-28",
    "INSCRITOS": "318000"
  },
  {
    "CANAL_ID": "UCwONybZQdULFV_ts2911Rqg",
    "ANO": 2025,
    "MES": 10,
    "DIA": "2025-10-31",
    "INSCRITOS": "758000"
  },
  {
    "CANAL_ID": "UC74FvQ6GtdwRmENGymLjqNA",
    "ANO": 2025,
    "MES": 10,
    "DIA": "2025-10-31",
    "INSCRITOS": "74300"
  },
  {
    "CANAL_ID": "UCMP3ETiqEPs0RMjxH57O5DQ",
    "ANO": 2025,
    "MES": 10,
    "DIA": "2025-10-31",
    "INSCRITOS": "6700"
  },
  {
    "CANAL_ID": "UCAbPPg9IVIjzPBAE7uGgd-g",
    "ANO": 2025,
    "MES": 10,
    "DIA": "2025-10-31",
    "INSCRITOS": "66100"
  },
  {
    "CANAL_ID": "UCWDeEIDAIi_oYKDiqwfGyRg",
    "ANO": 2025,
    "MES": 10,
    "DIA": "2025-10-31",
    "INSCRITOS": "500000"
  },
  {
    "CANAL_ID": "UC7k3dDEfclcB07Deoy41D6g",
    "ANO": 2025,
    "MES": 10,
    "DIA": "2025-10-31",
    "INSCRITOS": "41300"
  },
  {
    "CANAL_ID": "UCSXdP8V4jRaw-8YMTpa6glw",
    "ANO": 2025,
    "MES": 10,
    "DIA": "2025-10-31",
    "INSCRITOS": "308000"
  },
  {
    "CANAL_ID": "UCwONybZQdULFV_ts2911Rqg",
    "ANO": 2025,
    "MES": 9,
    "DIA": "2025-09-30",
    "INSCRITOS": "750000"
  },
  {
    "CANAL_ID": "UC74FvQ6GtdwRmENGymLjqNA",
    "ANO": 2025,
    "MES": 9,
    "DIA": "2025-09-30",
    "INSCRITOS": "74300"
  },
  {
    "CANAL_ID": "UCAbPPg9IVIjzPBAE7uGgd-g",
    "ANO": 2025,
    "MES": 9,
    "DIA": "2025-09-30",
    "INSCRITOS": "66100"
  },
  {
    "CANAL_ID": "UCMP3ETiqEPs0RMjxH57O5DQ",
    "ANO": 2025,
    "MES": 9,
    "DIA": "2025-09-30",
    "INSCRITOS": "6310"
  },
  {
    "CANAL_ID": "UCWDeEIDAIi_oYKDiqwfGyRg",
    "ANO": 2025,
    "MES": 9,
    "DIA": "2025-09-30",
    "INSCRITOS": "485000"
  },
  {
    "CANAL_ID": "UC7k3dDEfclcB07Deoy41D6g",
    "ANO": 2025,
    "MES": 9,
    "DIA": "2025-09-30",
    "INSCRITOS": "41400"
  },
  {
    "CANAL_ID": "UCSXdP8V4jRaw-8YMTpa6glw",
    "ANO": 2025,
    "MES": 9,
    "DIA": "2025-09-30",
    "INSCRITOS": "304000"
  },
  {
    "CANAL_ID": "UC74FvQ6GtdwRmENGymLjqNA",
    "ANO": 2025,
    "MES": 8,
    "DIA": "2025-08-31",
    "INSCRITOS": "74400"
  },
  {
    "CANAL_ID": "UCwONybZQdULFV_ts2911Rqg",
    "ANO": 2025,
    "MES": 8,
    "DIA": "2025-08-31",
    "INSCRITOS": "742000"
  },
  {
    "CANAL_ID": "UCAbPPg9IVIjzPBAE7uGgd-g",
    "ANO": 2025,
    "MES": 8,
    "DIA": "2025-08-31",
    "INSCRITOS": "65900"
  },
  {
    "CANAL_ID": "UCMP3ETiqEPs0RMjxH57O5DQ",
    "ANO": 2025,
    "MES": 8,
    "DIA": "2025-08-31",
    "INSCRITOS": "5920"
  },
  {
    "CANAL_ID": "UCWDeEIDAIi_oYKDiqwfGyRg",
    "ANO": 2025,
    "MES": 8,
    "DIA": "2025-08-31",
    "INSCRITOS": "470000"
  },
  {
    "CANAL_ID": "UC7k3dDEfclcB07Deoy41D6g",
    "ANO": 2025,
    "MES": 8,
    "DIA": "2025-08-31",
    "INSCRITOS": "41400"
  },
  {
    "CANAL_ID": "UCSXdP8V4jRaw-8YMTpa6glw",
    "ANO": 2025,
    "MES": 8,
    "DIA": "2025-08-31",
    "INSCRITOS": "299000"
  },
  {
    "CANAL_ID": "UC74FvQ6GtdwRmENGymLjqNA",
    "ANO": 2025,
    "MES": 7,
    "DIA": "2025-07-31",
    "INSCRITOS": "74400"
  },
  {
    "CANAL_ID": "UCwONybZQdULFV_ts2911Rqg",
    "ANO": 2025,
    "MES": 7,
    "DIA": "2025-07-31",
    "INSCRITOS": "734000"
  },
  {
    "CANAL_ID": "UCAbPPg9IVIjzPBAE7uGgd-g",
    "ANO": 2025,
    "MES": 7,
    "DIA": "2025-07-31",
    "INSCRITOS": "65800"
  },
  {
    "CANAL_ID": "UCWDeEIDAIi_oYKDiqwfGyRg",
    "ANO": 2025,
    "MES": 7,
    "DIA": "2025-07-31",
    "INSCRITOS": "464000"
  },
  {
    "CANAL_ID": "UC7k3dDEfclcB07Deoy41D6g",
    "ANO": 2025,
    "MES": 7,
    "DIA": "2025-07-31",
    "INSCRITOS": "41400"
  },
  {
    "CANAL_ID": "UCSXdP8V4jRaw-8YMTpa6glw",
    "ANO": 2025,
    "MES": 7,
    "DIA": "2025-07-31",
    "INSCRITOS": "292000"
  }
]