[
  {
    "DT_SNAPSHOT": "2026-05-14",
    "CANAL_ID": "UC8mDF5mWNGE-Kpfcvnn0bUg",
    "CANAL_NOME": "Me Poupe!",
    "CANAL_HANDLE": "@mepoupe",
    "TIPO": "concorrente",
    "BU": "Redes Sociais",
    "SUBSCRIBERS": 7730000,
    "VIEW_COUNT": 610772658,
    "VIDEO_COUNT": 2349,
    "SHARE_SUBSCRIBERS_PCT": "23.29",
    "SHARE_VIEWS_PCT": "15.53",
    "DELTA_SUBSCRIBERS_DOD": 0
  },
  {
    "DT_SNAPSHOT": "2026-05-14",
    "CANAL_ID": "UCT4nDeU5pv1XIGySbSK-GgA",
    "CANAL_NOME": "O Primo Rico",
    "CANAL_HANDLE": "@primorico",
    "TIPO": "concorrente",
    "BU": "Redes Sociais",
    "SUBSCRIBERS": 7610000,
    "VIEW_COUNT": 572122114,
    "VIDEO_COUNT": 1644,
    "SHARE_SUBSCRIBERS_PCT": "22.92",
    "SHARE_VIEWS_PCT": "14.54",
    "DELTA_SUBSCRIBERS_DOD": 0
  },
  {
    "DT_SNAPSHOT": "2026-05-14",
    "CANAL_ID": "UCjt5Mt-yVu_R8LfuiLcd5KA",
    "CANAL_NOME": "Cafe com Ferri",
    "CANAL_HANDLE": "@podcastcafecomferri",
    "TIPO": "concorrente",
    "BU": "Redes Sociais",
    "SUBSCRIBERS": 6920000,
    "VIEW_COUNT": 157791736,
    "VIDEO_COUNT": 1277,
    "SHARE_SUBSCRIBERS_PCT": "20.85",
    "SHARE_VIEWS_PCT": "4.01",
    "DELTA_SUBSCRIBERS_DOD": 10000
  },
  {
    "DT_SNAPSHOT": "2026-05-14",
    "CANAL_ID": "UCCE-jo1GvBJqyj1b287h7jA",
    "CANAL_NOME": "Bruno Perini",
    "CANAL_HANDLE": "@brunoperini",
    "TIPO": "concorrente",
    "BU": "Redes Sociais",
    "SUBSCRIBERS": 2070000,
    "VIEW_COUNT": 472585847,
    "VIDEO_COUNT": 2355,
    "SHARE_SUBSCRIBERS_PCT": "6.24",
    "SHARE_VIEWS_PCT": "12.01",
    "DELTA_SUBSCRIBERS_DOD": 0
  },
  {
    "DT_SNAPSHOT": "2026-05-14",
    "CANAL_ID": "UCM3vJxmuJJkk1r0yzFI9eZg",
    "CANAL_NOME": "Investidor Sardinha",
    "CANAL_HANDLE": "@investidorsardinha",
    "TIPO": "concorrente",
    "BU": "Asset,Redes Sociais",
    "SUBSCRIBERS": 1650000,
    "VIEW_COUNT": 307988532,
    "VIDEO_COUNT": 3104,
    "SHARE_SUBSCRIBERS_PCT": "4.97",
    "SHARE_VIEWS_PCT": "7.83",
    "DELTA_SUBSCRIBERS_DOD": 0
  },
  {
    "DT_SNAPSHOT": "2026-05-14",
    "CANAL_ID": "UCE5Uu3nZlVbTur6xwhdoKhg",
    "CANAL_NOME": "BTG Pactual",
    "CANAL_HANDLE": "@btgpactual",
    "TIPO": "concorrente",
    "BU": "Redes Sociais",
    "SUBSCRIBERS": 1270000,
    "VIEW_COUNT": 220465204,
    "VIDEO_COUNT": 2844,
    "SHARE_SUBSCRIBERS_PCT": "3.83",
    "SHARE_VIEWS_PCT": "5.60",
    "DELTA_SUBSCRIBERS_DOD": 0
  },
  {
    "DT_SNAPSHOT": "2026-05-14",
    "CANAL_ID": "UCrp0zmecZ3TNV8FSR-tjv7A",
    "CANAL_NOME": "Economista Sincero",
    "CANAL_HANDLE": "@economistasincero",
    "TIPO": "concorrente",
    "BU": "Redes Sociais",
    "SUBSCRIBERS": 1270000,
    "VIEW_COUNT": 274862476,
    "VIDEO_COUNT": 4241,
    "SHARE_SUBSCRIBERS_PCT": "3.83",
    "SHARE_VIEWS_PCT": "6.99",
    "DELTA_SUBSCRIBERS_DOD": 0
  },
  {
    "DT_SNAPSHOT": "2026-05-14",
    "CANAL_ID": "UCu79AeVqrq42vmSIp1OHyfA",
    "CANAL_NOME": "Empiricus",
    "CANAL_HANDLE": "@empiricus",
    "TIPO": "concorrente",
    "BU": "Research",
    "SUBSCRIBERS": 1090000,
    "VIEW_COUNT": 98446044,
    "VIDEO_COUNT": 2457,
    "SHARE_SUBSCRIBERS_PCT": "3.28",
    "SHARE_VIEWS_PCT": "2.50",
    "DELTA_SUBSCRIBERS_DOD": 0
  },
  {
    "DT_SNAPSHOT": "2026-05-14",
    "CANAL_ID": "UCwONybZQdULFV_ts2911Rqg",
    "CANAL_NOME": "Tiago Reis (Suno)",
    "CANAL_HANDLE": "@tiagoreis",
    "TIPO": "proprio",
    "BU": "Research,Asset",
    "SUBSCRIBERS": 816000,
    "VIEW_COUNT": 117175490,
    "VIDEO_COUNT": 4383,
    "SHARE_SUBSCRIBERS_PCT": "2.46",
    "SHARE_VIEWS_PCT": "2.98",
    "DELTA_SUBSCRIBERS_DOD": 0
  },
  {
    "DT_SNAPSHOT": "2026-05-14",
    "CANAL_ID": "UCxm0tptjIc76-i26EKQ9NpA",
    "CANAL_NOME": "InfoMoney",
    "CANAL_HANDLE": "@infomoney",
    "TIPO": "concorrente",
    "BU": "Redes Sociais",
    "SUBSCRIBERS": 736000,
    "VIEW_COUNT": 158544207,
    "VIDEO_COUNT": 19143,
    "SHARE_SUBSCRIBERS_PCT": "2.22",
    "SHARE_VIEWS_PCT": "4.03",
    "DELTA_SUBSCRIBERS_DOD": 0
  },
  {
    "DT_SNAPSHOT": "2026-05-14",
    "CANAL_ID": "UCWDeEIDAIi_oYKDiqwfGyRg",
    "CANAL_NOME": "Suno Research",
    "CANAL_HANDLE": "@gruposuno",
    "TIPO": "proprio",
    "BU": "Research,Asset,Redes Sociais",
    "SUBSCRIBERS": 518000,
    "VIEW_COUNT": 108288710,
    "VIDEO_COUNT": 4700,
    "SHARE_SUBSCRIBERS_PCT": "1.56",
    "SHARE_VIEWS_PCT": "2.75",
    "DELTA_SUBSCRIBERS_DOD": 0
  },
  {
    "DT_SNAPSHOT": "2026-05-14",
    "CANAL_ID": "UCf15n72n6pV0RK6-GOi1s1Q",
    "CANAL_NOME": "XP Investimentos",
    "CANAL_HANDLE": "@xp_oficial",
    "TIPO": "concorrente",
    "BU": "Redes Sociais",
    "SUBSCRIBERS": 487000,
    "VIEW_COUNT": 710318871,
    "VIDEO_COUNT": 3904,
    "SHARE_SUBSCRIBERS_PCT": "1.47",
    "SHARE_VIEWS_PCT": "18.06",
    "DELTA_SUBSCRIBERS_DOD": 0
  },
  {
    "DT_SNAPSHOT": "2026-05-14",
    "CANAL_ID": "UCSXdP8V4jRaw-8YMTpa6glw",
    "CANAL_NOME": "Suno Baroni",
    "CANAL_HANDLE": "@professorbaroni",
    "TIPO": "proprio",
    "BU": "Asset,Redes Sociais",
    "SUBSCRIBERS": 349000,
    "VIEW_COUNT": 43085840,
    "VIDEO_COUNT": 3266,
    "SHARE_SUBSCRIBERS_PCT": "1.05",
    "SHARE_VIEWS_PCT": "1.10",
    "DELTA_SUBSCRIBERS_DOD": 0
  },
  {
    "DT_SNAPSHOT": "2026-05-14",
    "CANAL_ID": "UCsU0E4F3RxVOSjWlIMieReA",
    "CANAL_NOME": "Nord Investimentos",
    "CANAL_HANDLE": "@nordinvestimentos",
    "TIPO": "concorrente",
    "BU": "Research,Redes Sociais",
    "SUBSCRIBERS": 273000,
    "VIEW_COUNT": 20500577,
    "VIDEO_COUNT": 1227,
    "SHARE_SUBSCRIBERS_PCT": "0.82",
    "SHARE_VIEWS_PCT": "0.52",
    "DELTA_SUBSCRIBERS_DOD": 0
  },
  {
    "DT_SNAPSHOT": "2026-05-14",
    "CANAL_ID": "UCuP3yzTmY6AWjIljW0GPuPg",
    "CANAL_NOME": "Kinea Investimentos",
    "CANAL_HANDLE": "@kineainvestimentos",
    "TIPO": "concorrente",
    "BU": "Asset",
    "SUBSCRIBERS": 90800,
    "VIEW_COUNT": 32503351,
    "VIDEO_COUNT": 1366,
    "SHARE_SUBSCRIBERS_PCT": "0.27",
    "SHARE_VIEWS_PCT": "0.83",
    "DELTA_SUBSCRIBERS_DOD": 0
  },
  {
    "DT_SNAPSHOT": "2026-05-14",
    "CANAL_ID": "UCjZsV-DSJVU2i8M9Bl56ZQg",
    "CANAL_NOME": "TRX Investimentos",
    "CANAL_HANDLE": "@trxinvestimentos2945",
    "TIPO": "concorrente",
    "BU": "Asset",
    "SUBSCRIBERS": 82500,
    "VIEW_COUNT": 838416,
    "VIDEO_COUNT": 142,
    "SHARE_SUBSCRIBERS_PCT": "0.25",
    "SHARE_VIEWS_PCT": "0.02",
    "DELTA_SUBSCRIBERS_DOD": 0
  },
  {
    "DT_SNAPSHOT": "2026-05-14",
    "CANAL_ID": "UC74FvQ6GtdwRmENGymLjqNA",
    "CANAL_NOME": "Suno Noticias",
    "CANAL_HANDLE": "@sunonoticias",
    "TIPO": "proprio",
    "BU": "Redes Sociais",
    "SUBSCRIBERS": 73800,
    "VIEW_COUNT": 8693244,
    "VIDEO_COUNT": 3412,
    "SHARE_SUBSCRIBERS_PCT": "0.22",
    "SHARE_VIEWS_PCT": "0.22",
    "DELTA_SUBSCRIBERS_DOD": 0
  },
  {
    "DT_SNAPSHOT": "2026-05-14",
    "CANAL_ID": "UCAbPPg9IVIjzPBAE7uGgd-g",
    "CANAL_NOME": "Funds Explorer",
    "CANAL_HANDLE": "@fundsexplorer",
    "TIPO": "proprio",
    "BU": "Asset",
    "SUBSCRIBERS": 67500,
    "VIEW_COUNT": 2697096,
    "VIDEO_COUNT": 655,
    "SHARE_SUBSCRIBERS_PCT": "0.20",
    "SHARE_VIEWS_PCT": "0.07",
    "DELTA_SUBSCRIBERS_DOD": 100
  },
  {
    "DT_SNAPSHOT": "2026-05-14",
    "CANAL_ID": "UC7k3dDEfclcB07Deoy41D6g",
    "CANAL_NOME": "Status Invest",
    "CANAL_HANDLE": "@statusinvest",
    "TIPO": "proprio",
    "BU": "Asset",
    "SUBSCRIBERS": 61700,
    "VIEW_COUNT": 3122160,
    "VIDEO_COUNT": 644,
    "SHARE_SUBSCRIBERS_PCT": "0.19",
    "SHARE_VIEWS_PCT": "0.08",
    "DELTA_SUBSCRIBERS_DOD": 0
  },
  {
    "DT_SNAPSHOT": "2026-05-14",
    "CANAL_ID": "UC3F7xGujyP59SsrzhdO9aAA",
    "CANAL_NOME": "BTG Asset Management",
    "CANAL_HANDLE": "@btgpactualassetmanagement",
    "TIPO": "concorrente",
    "BU": "Asset",
    "SUBSCRIBERS": 10700,
    "VIEW_COUNT": 7865664,
    "VIDEO_COUNT": 538,
    "SHARE_SUBSCRIBERS_PCT": "0.03",
    "SHARE_VIEWS_PCT": "0.20",
    "DELTA_SUBSCRIBERS_DOD": 0
  },
  {
    "DT_SNAPSHOT": "2026-05-14",
    "CANAL_ID": "UCMP3ETiqEPs0RMjxH57O5DQ",
    "CANAL_NOME": "Suno Asset",
    "CANAL_HANDLE": "@sunoasset",
    "TIPO": "proprio",
    "BU": "Asset",
    "SUBSCRIBERS": 8820,
    "VIEW_COUNT": 4818275,
    "VIDEO_COUNT": 637,
    "SHARE_SUBSCRIBERS_PCT": "0.03",
    "SHARE_VIEWS_PCT": "0.12",
    "DELTA_SUBSCRIBERS_DOD": 0
  },
  {
    "DT_SNAPSHOT": "2026-05-14",
    "CANAL_ID": "UC-jNfX6MhcLLfMATynctQBQ",
    "CANAL_NOME": "XP Asset Management",
    "CANAL_HANDLE": "@xpassetmanagement",
    "TIPO": "concorrente",
    "BU": "Asset",
    "SUBSCRIBERS": 8270,
    "VIEW_COUNT": 255602,
    "VIDEO_COUNT": 734,
    "SHARE_SUBSCRIBERS_PCT": "0.02",
    "SHARE_VIEWS_PCT": "0.01",
    "DELTA_SUBSCRIBERS_DOD": 0
  },
  {
    "DT_SNAPSHOT": "2026-05-14",
    "CANAL_ID": "UCfeFPKDC7gEP_BOaIdY46jw",
    "CANAL_NOME": "RBR Asset Management",
    "CANAL_HANDLE": "@rbrassetmanagement",
    "TIPO": "concorrente",
    "BU": "Asset",
    "SUBSCRIBERS": 2930,
    "VIEW_COUNT": 108813,
    "VIDEO_COUNT": 125,
    "SHARE_SUBSCRIBERS_PCT": "0.01",
    "SHARE_VIEWS_PCT": "0.00",
    "DELTA_SUBSCRIBERS_DOD": -10
  },
  {
    "DT_SNAPSHOT": "2026-05-13",
    "CANAL_ID": "UC8mDF5mWNGE-Kpfcvnn0bUg",
    "CANAL_NOME": "Me Poupe!",
    "CANAL_HANDLE": "@mepoupe",
    "TIPO": "concorrente",
    "BU": "Redes Sociais",
    "SUBSCRIBERS": 7730000,
    "VIEW_COUNT": 610666121,
    "VIDEO_COUNT": 2347,
    "SHARE_SUBSCRIBERS_PCT": "23.29",
    "SHARE_VIEWS_PCT": "15.53",
    "DELTA_SUBSCRIBERS_DOD": 0
  },
  {
    "DT_SNAPSHOT": "2026-05-13",
    "CANAL_ID": "UCT4nDeU5pv1XIGySbSK-GgA",
    "CANAL_NOME": "O Primo Rico",
    "CANAL_HANDLE": "@primorico",
    "TIPO": "concorrente",
    "BU": "Redes Sociais",
    "SUBSCRIBERS": 7610000,
    "VIEW_COUNT": 571889596,
    "VIDEO_COUNT": 1641,
    "SHARE_SUBSCRIBERS_PCT": "22.93",
    "SHARE_VIEWS_PCT": "14.54",
    "DELTA_SUBSCRIBERS_DOD": 0
  },
  {
    "DT_SNAPSHOT": "2026-05-13",
    "CANAL_ID": "UCjt5Mt-yVu_R8LfuiLcd5KA",
    "CANAL_NOME": "Cafe com Ferri",
    "CANAL_HANDLE": "@podcastcafecomferri",
    "TIPO": "concorrente",
    "BU": "Redes Sociais",
    "SUBSCRIBERS": 6910000,
    "VIEW_COUNT": 157534252,
    "VIDEO_COUNT": 1272,
    "SHARE_SUBSCRIBERS_PCT": "20.82",
    "SHARE_VIEWS_PCT": "4.01",
    "DELTA_SUBSCRIBERS_DOD": 0
  },
  {
    "DT_SNAPSHOT": "2026-05-13",
    "CANAL_ID": "UCCE-jo1GvBJqyj1b287h7jA",
    "CANAL_NOME": "Bruno Perini",
    "CANAL_HANDLE": "@brunoperini",
    "TIPO": "concorrente",
    "BU": "Redes Sociais",
    "SUBSCRIBERS": 2070000,
    "VIEW_COUNT": 472463337,
    "VIDEO_COUNT": 2354,
    "SHARE_SUBSCRIBERS_PCT": "6.24",
    "SHARE_VIEWS_PCT": "12.01",
    "DELTA_SUBSCRIBERS_DOD": 0
  },
  {
    "DT_SNAPSHOT": "2026-05-13",
    "CANAL_ID": "UCM3vJxmuJJkk1r0yzFI9eZg",
    "CANAL_NOME": "Investidor Sardinha",
    "CANAL_HANDLE": "@investidorsardinha",
    "TIPO": "concorrente",
    "BU": "Asset,Redes Sociais",
    "SUBSCRIBERS": 1650000,
    "VIEW_COUNT": 307694742,
    "VIDEO_COUNT": 3102,
    "SHARE_SUBSCRIBERS_PCT": "4.97",
    "SHARE_VIEWS_PCT": "7.82",
    "DELTA_SUBSCRIBERS_DOD": 10000
  },
  {
    "DT_SNAPSHOT": "2026-05-13",
    "CANAL_ID": "UCE5Uu3nZlVbTur6xwhdoKhg",
    "CANAL_NOME": "BTG Pactual",
    "CANAL_HANDLE": "@btgpactual",
    "TIPO": "concorrente",
    "BU": "Redes Sociais",
    "SUBSCRIBERS": 1270000,
    "VIEW_COUNT": 220329148,
    "VIDEO_COUNT": 2842,
    "SHARE_SUBSCRIBERS_PCT": "3.83",
    "SHARE_VIEWS_PCT": "5.60",
    "DELTA_SUBSCRIBERS_DOD": 0
  },
  {
    "DT_SNAPSHOT": "2026-05-13",
    "CANAL_ID": "UCrp0zmecZ3TNV8FSR-tjv7A",
    "CANAL_NOME": "Economista Sincero",
    "CANAL_HANDLE": "@economistasincero",
    "TIPO": "concorrente",
    "BU": "Redes Sociais",
    "SUBSCRIBERS": 1270000,
    "VIEW_COUNT": 274712423,
    "VIDEO_COUNT": 4238,
    "SHARE_SUBSCRIBERS_PCT": "3.83",
    "SHARE_VIEWS_PCT": "6.99",
    "DELTA_SUBSCRIBERS_DOD": 0
  },
  {
    "DT_SNAPSHOT": "2026-05-13",
    "CANAL_ID": "UCu79AeVqrq42vmSIp1OHyfA",
    "CANAL_NOME": "Empiricus",
    "CANAL_HANDLE": "@empiricus",
    "TIPO": "concorrente",
    "BU": "Research",
    "SUBSCRIBERS": 1090000,
    "VIEW_COUNT": 98431845,
    "VIDEO_COUNT": 2455,
    "SHARE_SUBSCRIBERS_PCT": "3.28",
    "SHARE_VIEWS_PCT": "2.50",
    "DELTA_SUBSCRIBERS_DOD": 0
  },
  {
    "DT_SNAPSHOT": "2026-05-13",
    "CANAL_ID": "UCwONybZQdULFV_ts2911Rqg",
    "CANAL_NOME": "Tiago Reis (Suno)",
    "CANAL_HANDLE": "@tiagoreis",
    "TIPO": "proprio",
    "BU": "Research,Asset",
    "SUBSCRIBERS": 816000,
    "VIEW_COUNT": 117408512,
    "VIDEO_COUNT": 4383,
    "SHARE_SUBSCRIBERS_PCT": "2.46",
    "SHARE_VIEWS_PCT": "2.99",
    "DELTA_SUBSCRIBERS_DOD": 0
  },
  {
    "DT_SNAPSHOT": "2026-05-13",
    "CANAL_ID": "UCxm0tptjIc76-i26EKQ9NpA",
    "CANAL_NOME": "InfoMoney",
    "CANAL_HANDLE": "@infomoney",
    "TIPO": "concorrente",
    "BU": "Redes Sociais",
    "SUBSCRIBERS": 736000,
    "VIEW_COUNT": 158304050,
    "VIDEO_COUNT": 19099,
    "SHARE_SUBSCRIBERS_PCT": "2.22",
    "SHARE_VIEWS_PCT": "4.03",
    "DELTA_SUBSCRIBERS_DOD": 1000
  },
  {
    "DT_SNAPSHOT": "2026-05-13",
    "CANAL_ID": "UCWDeEIDAIi_oYKDiqwfGyRg",
    "CANAL_NOME": "Suno Research",
    "CANAL_HANDLE": "@gruposuno",
    "TIPO": "proprio",
    "BU": "Research,Asset,Redes Sociais",
    "SUBSCRIBERS": 518000,
    "VIEW_COUNT": 108280967,
    "VIDEO_COUNT": 4691,
    "SHARE_SUBSCRIBERS_PCT": "1.56",
    "SHARE_VIEWS_PCT": "2.75",
    "DELTA_SUBSCRIBERS_DOD": 0
  },
  {
    "DT_SNAPSHOT": "2026-05-13",
    "CANAL_ID": "UCf15n72n6pV0RK6-GOi1s1Q",
    "CANAL_NOME": "XP Investimentos",
    "CANAL_HANDLE": "@xp_oficial",
    "TIPO": "concorrente",
    "BU": "Redes Sociais",
    "SUBSCRIBERS": 487000,
    "VIEW_COUNT": 710311057,
    "VIDEO_COUNT": 3901,
    "SHARE_SUBSCRIBERS_PCT": "1.47",
    "SHARE_VIEWS_PCT": "18.06",
    "DELTA_SUBSCRIBERS_DOD": 0
  },
  {
    "DT_SNAPSHOT": "2026-05-13",
    "CANAL_ID": "UCSXdP8V4jRaw-8YMTpa6glw",
    "CANAL_NOME": "Suno Baroni",
    "CANAL_HANDLE": "@professorbaroni",
    "TIPO": "proprio",
    "BU": "Asset,Redes Sociais",
    "SUBSCRIBERS": 349000,
    "VIEW_COUNT": 43071235,
    "VIDEO_COUNT": 3264,
    "SHARE_SUBSCRIBERS_PCT": "1.05",
    "SHARE_VIEWS_PCT": "1.10",
    "DELTA_SUBSCRIBERS_DOD": 0
  },
  {
    "DT_SNAPSHOT": "2026-05-13",
    "CANAL_ID": "UCsU0E4F3RxVOSjWlIMieReA",
    "CANAL_NOME": "Nord Investimentos",
    "CANAL_HANDLE": "@nordinvestimentos",
    "TIPO": "concorrente",
    "BU": "Research,Redes Sociais",
    "SUBSCRIBERS": 273000,
    "VIEW_COUNT": 20497056,
    "VIDEO_COUNT": 1227,
    "SHARE_SUBSCRIBERS_PCT": "0.82",
    "SHARE_VIEWS_PCT": "0.52",
    "DELTA_SUBSCRIBERS_DOD": 0
  },
  {
    "DT_SNAPSHOT": "2026-05-13",
    "CANAL_ID": "UCuP3yzTmY6AWjIljW0GPuPg",
    "CANAL_NOME": "Kinea Investimentos",
    "CANAL_HANDLE": "@kineainvestimentos",
    "TIPO": "concorrente",
    "BU": "Asset",
    "SUBSCRIBERS": 90800,
    "VIEW_COUNT": 32480096,
    "VIDEO_COUNT": 1366,
    "SHARE_SUBSCRIBERS_PCT": "0.27",
    "SHARE_VIEWS_PCT": "0.83",
    "DELTA_SUBSCRIBERS_DOD": null
  },
  {
    "DT_SNAPSHOT": "2026-05-13",
    "CANAL_ID": "UCjZsV-DSJVU2i8M9Bl56ZQg",
    "CANAL_NOME": "TRX Investimentos",
    "CANAL_HANDLE": "@trxinvestimentos2945",
    "TIPO": "concorrente",
    "BU": "Asset",
    "SUBSCRIBERS": 82500,
    "VIEW_COUNT": 780218,
    "VIDEO_COUNT": 142,
    "SHARE_SUBSCRIBERS_PCT": "0.25",
    "SHARE_VIEWS_PCT": "0.02",
    "DELTA_SUBSCRIBERS_DOD": null
  },
  {
    "DT_SNAPSHOT": "2026-05-13",
    "CANAL_ID": "UC74FvQ6GtdwRmENGymLjqNA",
    "CANAL_NOME": "Suno Noticias",
    "CANAL_HANDLE": "@sunonoticias",
    "TIPO": "proprio",
    "BU": "Redes Sociais",
    "SUBSCRIBERS": 73800,
    "VIEW_COUNT": 8692886,
    "VIDEO_COUNT": 3412,
    "SHARE_SUBSCRIBERS_PCT": "0.22",
    "SHARE_VIEWS_PCT": "0.22",
    "DELTA_SUBSCRIBERS_DOD": 0
  },
  {
    "DT_SNAPSHOT": "2026-05-13",
    "CANAL_ID": "UCAbPPg9IVIjzPBAE7uGgd-g",
    "CANAL_NOME": "Funds Explorer",
    "CANAL_HANDLE": "@fundsexplorer",
    "TIPO": "proprio",
    "BU": "Asset",
    "SUBSCRIBERS": 67400,
    "VIEW_COUNT": 2696605,
    "VIDEO_COUNT": 654,
    "SHARE_SUBSCRIBERS_PCT": "0.20",
    "SHARE_VIEWS_PCT": "0.07",
    "DELTA_SUBSCRIBERS_DOD": 0
  },
  {
    "DT_SNAPSHOT": "2026-05-13",
    "CANAL_ID": "UC7k3dDEfclcB07Deoy41D6g",
    "CANAL_NOME": "Status Invest",
    "CANAL_HANDLE": "@statusinvest",
    "TIPO": "proprio",
    "BU": "Asset",
    "SUBSCRIBERS": 61700,
    "VIEW_COUNT": 3120075,
    "VIDEO_COUNT": 643,
    "SHARE_SUBSCRIBERS_PCT": "0.19",
    "SHARE_VIEWS_PCT": "0.08",
    "DELTA_SUBSCRIBERS_DOD": 100
  },
  {
    "DT_SNAPSHOT": "2026-05-13",
    "CANAL_ID": "UC3F7xGujyP59SsrzhdO9aAA",
    "CANAL_NOME": "BTG Asset Management",
    "CANAL_HANDLE": "@btgpactualassetmanagement",
    "TIPO": "concorrente",
    "BU": "Asset",
    "SUBSCRIBERS": 10700,
    "VIEW_COUNT": 7836045,
    "VIDEO_COUNT": 537,
    "SHARE_SUBSCRIBERS_PCT": "0.03",
    "SHARE_VIEWS_PCT": "0.20",
    "DELTA_SUBSCRIBERS_DOD": null
  },
  {
    "DT_SNAPSHOT": "2026-05-13",
    "CANAL_ID": "UCMP3ETiqEPs0RMjxH57O5DQ",
    "CANAL_NOME": "Suno Asset",
    "CANAL_HANDLE": "@sunoasset",
    "TIPO": "proprio",
    "BU": "Asset",
    "SUBSCRIBERS": 8820,
    "VIEW_COUNT": 4807672,
    "VIDEO_COUNT": 637,
    "SHARE_SUBSCRIBERS_PCT": "0.03",
    "SHARE_VIEWS_PCT": "0.12",
    "DELTA_SUBSCRIBERS_DOD": 20
  },
  {
    "DT_SNAPSHOT": "2026-05-13",
    "CANAL_ID": "UC-jNfX6MhcLLfMATynctQBQ",
    "CANAL_NOME": "XP Asset Management",
    "CANAL_HANDLE": "@xpassetmanagement",
    "TIPO": "concorrente",
    "BU": "Asset",
    "SUBSCRIBERS": 8270,
    "VIEW_COUNT": 255494,
    "VIDEO_COUNT": 734,
    "SHARE_SUBSCRIBERS_PCT": "0.02",
    "SHARE_VIEWS_PCT": "0.01",
    "DELTA_SUBSCRIBERS_DOD": null
  },
  {
    "DT_SNAPSHOT": "2026-05-13",
    "CANAL_ID": "UCfeFPKDC7gEP_BOaIdY46jw",
    "CANAL_NOME": "RBR Asset Management",
    "CANAL_HANDLE": "@rbrassetmanagement",
    "TIPO": "concorrente",
    "BU": "Asset",
    "SUBSCRIBERS": 2940,
    "VIEW_COUNT": 108813,
    "VIDEO_COUNT": 125,
    "SHARE_SUBSCRIBERS_PCT": "0.01",
    "SHARE_VIEWS_PCT": "0.00",
    "DELTA_SUBSCRIBERS_DOD": null
  },
  {
    "DT_SNAPSHOT": "2026-05-12",
    "CANAL_ID": "UC8mDF5mWNGE-Kpfcvnn0bUg",
    "CANAL_NOME": "Me Poupe!",
    "CANAL_HANDLE": "@mepoupe",
    "TIPO": "concorrente",
    "BU": "Redes Sociais",
    "SUBSCRIBERS": 7730000,
    "VIEW_COUNT": 610543724,
    "VIDEO_COUNT": 2345,
    "SHARE_SUBSCRIBERS_PCT": "23.44",
    "SHARE_VIEWS_PCT": "15.70",
    "DELTA_SUBSCRIBERS_DOD": 0
  },
  {
    "DT_SNAPSHOT": "2026-05-12",
    "CANAL_ID": "UCT4nDeU5pv1XIGySbSK-GgA",
    "CANAL_NOME": "O Primo Rico",
    "CANAL_HANDLE": "@primorico",
    "TIPO": "concorrente",
    "BU": "Redes Sociais",
    "SUBSCRIBERS": 7610000,
    "VIEW_COUNT": 571654638,
    "VIDEO_COUNT": 1639,
    "SHARE_SUBSCRIBERS_PCT": "23.07",
    "SHARE_VIEWS_PCT": "14.70",
    "DELTA_SUBSCRIBERS_DOD": 0
  },
  {
    "DT_SNAPSHOT": "2026-05-12",
    "CANAL_ID": "UCjt5Mt-yVu_R8LfuiLcd5KA",
    "CANAL_NOME": "Cafe com Ferri",
    "CANAL_HANDLE": "@podcastcafecomferri",
    "TIPO": "concorrente",
    "BU": "Redes Sociais",
    "SUBSCRIBERS": 6910000,
    "VIEW_COUNT": 157346979,
    "VIDEO_COUNT": 1272,
    "SHARE_SUBSCRIBERS_PCT": "20.95",
    "SHARE_VIEWS_PCT": "4.05",
    "DELTA_SUBSCRIBERS_DOD": 10000
  },
  {
    "DT_SNAPSHOT": "2026-05-12",
    "CANAL_ID": "UCCE-jo1GvBJqyj1b287h7jA",
    "CANAL_NOME": "Bruno Perini",
    "CANAL_HANDLE": "@brunoperini",
    "TIPO": "concorrente",
    "BU": "Redes Sociais",
    "SUBSCRIBERS": 2070000,
    "VIEW_COUNT": 472235631,
    "VIDEO_COUNT": 2353,
    "SHARE_SUBSCRIBERS_PCT": "6.28",
    "SHARE_VIEWS_PCT": "12.14",
    "DELTA_SUBSCRIBERS_DOD": 0
  },
  {
    "DT_SNAPSHOT": "2026-05-12",
    "CANAL_ID": "UCM3vJxmuJJkk1r0yzFI9eZg",
    "CANAL_NOME": "Investidor Sardinha",
    "CANAL_HANDLE": "@investidorsardinha",
    "TIPO": "concorrente",
    "BU": "Asset,Redes Sociais",
    "SUBSCRIBERS": 1640000,
    "VIEW_COUNT": 307460310,
    "VIDEO_COUNT": 3100,
    "SHARE_SUBSCRIBERS_PCT": "4.97",
    "SHARE_VIEWS_PCT": "7.91",
    "DELTA_SUBSCRIBERS_DOD": 0
  },
  {
    "DT_SNAPSHOT": "2026-05-12",
    "CANAL_ID": "UCrp0zmecZ3TNV8FSR-tjv7A",
    "CANAL_NOME": "Economista Sincero",
    "CANAL_HANDLE": "@economistasincero",
    "TIPO": "concorrente",
    "BU": "Redes Sociais",
    "SUBSCRIBERS": 1270000,
    "VIEW_COUNT": 274628178,
    "VIDEO_COUNT": 4234,
    "SHARE_SUBSCRIBERS_PCT": "3.85",
    "SHARE_VIEWS_PCT": "7.06",
    "DELTA_SUBSCRIBERS_DOD": 0
  },
  {
    "DT_SNAPSHOT": "2026-05-12",
    "CANAL_ID": "UCE5Uu3nZlVbTur6xwhdoKhg",
    "CANAL_NOME": "BTG Pactual",
    "CANAL_HANDLE": "@btgpactual",
    "TIPO": "concorrente",
    "BU": "Redes Sociais",
    "SUBSCRIBERS": 1270000,
    "VIEW_COUNT": 220102698,
    "VIDEO_COUNT": 2839,
    "SHARE_SUBSCRIBERS_PCT": "3.85",
    "SHARE_VIEWS_PCT": "5.66",
    "DELTA_SUBSCRIBERS_DOD": 0
  },
  {
    "DT_SNAPSHOT": "2026-05-12",
    "CANAL_ID": "UCu79AeVqrq42vmSIp1OHyfA",
    "CANAL_NOME": "Empiricus",
    "CANAL_HANDLE": "@empiricus",
    "TIPO": "concorrente",
    "BU": "Research",
    "SUBSCRIBERS": 1090000,
    "VIEW_COUNT": 98411726,
    "VIDEO_COUNT": 2450,
    "SHARE_SUBSCRIBERS_PCT": "3.31",
    "SHARE_VIEWS_PCT": "2.53",
    "DELTA_SUBSCRIBERS_DOD": 0
  },
  {
    "DT_SNAPSHOT": "2026-05-12",
    "CANAL_ID": "UCwONybZQdULFV_ts2911Rqg",
    "CANAL_NOME": "Tiago Reis (Suno)",
    "CANAL_HANDLE": "@tiagoreis",
    "TIPO": "proprio",
    "BU": "Research,Asset",
    "SUBSCRIBERS": 816000,
    "VIEW_COUNT": 117399635,
    "VIDEO_COUNT": 4383,
    "SHARE_SUBSCRIBERS_PCT": "2.47",
    "SHARE_VIEWS_PCT": "3.02",
    "DELTA_SUBSCRIBERS_DOD": 0
  },
  {
    "DT_SNAPSHOT": "2026-05-12",
    "CANAL_ID": "UCxm0tptjIc76-i26EKQ9NpA",
    "CANAL_NOME": "InfoMoney",
    "CANAL_HANDLE": "@infomoney",
    "TIPO": "concorrente",
    "BU": "Redes Sociais",
    "SUBSCRIBERS": 735000,
    "VIEW_COUNT": 158131362,
    "VIDEO_COUNT": 19068,
    "SHARE_SUBSCRIBERS_PCT": "2.23",
    "SHARE_VIEWS_PCT": "4.07",
    "DELTA_SUBSCRIBERS_DOD": 0
  },
  {
    "DT_SNAPSHOT": "2026-05-12",
    "CANAL_ID": "UCWDeEIDAIi_oYKDiqwfGyRg",
    "CANAL_NOME": "Suno Research",
    "CANAL_HANDLE": "@gruposuno",
    "TIPO": "proprio",
    "BU": "Research,Asset,Redes Sociais",
    "SUBSCRIBERS": 518000,
    "VIEW_COUNT": 108274130,
    "VIDEO_COUNT": 4690,
    "SHARE_SUBSCRIBERS_PCT": "1.57",
    "SHARE_VIEWS_PCT": "2.78",
    "DELTA_SUBSCRIBERS_DOD": 0
  },
  {
    "DT_SNAPSHOT": "2026-05-12",
    "CANAL_ID": "UCf15n72n6pV0RK6-GOi1s1Q",
    "CANAL_NOME": "XP Investimentos",
    "CANAL_HANDLE": "@xp_oficial",
    "TIPO": "concorrente",
    "BU": "Redes Sociais",
    "SUBSCRIBERS": 487000,
    "VIEW_COUNT": 710300015,
    "VIDEO_COUNT": 3897,
    "SHARE_SUBSCRIBERS_PCT": "1.48",
    "SHARE_VIEWS_PCT": "18.26",
    "DELTA_SUBSCRIBERS_DOD": 0
  },
  {
    "DT_SNAPSHOT": "2026-05-12",
    "CANAL_ID": "UCSXdP8V4jRaw-8YMTpa6glw",
    "CANAL_NOME": "Suno Baroni",
    "CANAL_HANDLE": "@professorbaroni",
    "TIPO": "proprio",
    "BU": "Asset,Redes Sociais",
    "SUBSCRIBERS": 349000,
    "VIEW_COUNT": 43056613,
    "VIDEO_COUNT": 3261,
    "SHARE_SUBSCRIBERS_PCT": "1.06",
    "SHARE_VIEWS_PCT": "1.11",
    "DELTA_SUBSCRIBERS_DOD": 0
  },
  {
    "DT_SNAPSHOT": "2026-05-12",
    "CANAL_ID": "UCsU0E4F3RxVOSjWlIMieReA",
    "CANAL_NOME": "Nord Investimentos",
    "CANAL_HANDLE": "@nordinvestimentos",
    "TIPO": "concorrente",
    "BU": "Research,Redes Sociais",
    "SUBSCRIBERS": 273000,
    "VIEW_COUNT": 20492603,
    "VIDEO_COUNT": 1227,
    "SHARE_SUBSCRIBERS_PCT": "0.83",
    "SHARE_VIEWS_PCT": "0.53",
    "DELTA_SUBSCRIBERS_DOD": 0
  },
  {
    "DT_SNAPSHOT": "2026-05-12",
    "CANAL_ID": "UC74FvQ6GtdwRmENGymLjqNA",
    "CANAL_NOME": "Suno Noticias",
    "CANAL_HANDLE": "@sunonoticias",
    "TIPO": "proprio",
    "BU": "Redes Sociais",
    "SUBSCRIBERS": 73800,
    "VIEW_COUNT": 8692558,
    "VIDEO_COUNT": 3412,
    "SHARE_SUBSCRIBERS_PCT": "0.22",
    "SHARE_VIEWS_PCT": "0.22",
    "DELTA_SUBSCRIBERS_DOD": 0
  },
  {
    "DT_SNAPSHOT": "2026-05-12",
    "CANAL_ID": "UCAbPPg9IVIjzPBAE7uGgd-g",
    "CANAL_NOME": "Funds Explorer",
    "CANAL_HANDLE": "@fundsexplorer",
    "TIPO": "proprio",
    "BU": "Asset",
    "SUBSCRIBERS": 67400,
    "VIEW_COUNT": 2692513,
    "VIDEO_COUNT": 653,
    "SHARE_SUBSCRIBERS_PCT": "0.20",
    "SHARE_VIEWS_PCT": "0.07",
    "DELTA_SUBSCRIBERS_DOD": 0
  },
  {
    "DT_SNAPSHOT": "2026-05-12",
    "CANAL_ID": "UC7k3dDEfclcB07Deoy41D6g",
    "CANAL_NOME": "Status Invest",
    "CANAL_HANDLE": "@statusinvest",
    "TIPO": "proprio",
    "BU": "Asset",
    "SUBSCRIBERS": 61600,
    "VIEW_COUNT": 3119374,
    "VIDEO_COUNT": 642,
    "SHARE_SUBSCRIBERS_PCT": "0.19",
    "SHARE_VIEWS_PCT": "0.08",
    "DELTA_SUBSCRIBERS_DOD": 0
  },
  {
    "DT_SNAPSHOT": "2026-05-12",
    "CANAL_ID": "UCMP3ETiqEPs0RMjxH57O5DQ",
    "CANAL_NOME": "Suno Asset",
    "CANAL_HANDLE": "@sunoasset",
    "TIPO": "proprio",
    "BU": "Asset",
    "SUBSCRIBERS": 8800,
    "VIEW_COUNT": 4787337,
    "VIDEO_COUNT": 638,
    "SHARE_SUBSCRIBERS_PCT": "0.03",
    "SHARE_VIEWS_PCT": "0.12",
    "DELTA_SUBSCRIBERS_DOD": 0
  },
  {
    "DT_SNAPSHOT": "2026-05-11",
    "CANAL_ID": "UC8mDF5mWNGE-Kpfcvnn0bUg",
    "CANAL_NOME": "Me Poupe!",
    "CANAL_HANDLE": "@mepoupe",
    "TIPO": "concorrente",
    "BU": "Redes Sociais",
    "SUBSCRIBERS": 7730000,
    "VIEW_COUNT": 610475838,
    "VIDEO_COUNT": 2342,
    "SHARE_SUBSCRIBERS_PCT": "23.45",
    "SHARE_VIEWS_PCT": "15.70",
    "DELTA_SUBSCRIBERS_DOD": 0
  },
  {
    "DT_SNAPSHOT": "2026-05-11",
    "CANAL_ID": "UCT4nDeU5pv1XIGySbSK-GgA",
    "CANAL_NOME": "O Primo Rico",
    "CANAL_HANDLE": "@primorico",
    "TIPO": "concorrente",
    "BU": "Redes Sociais",
    "SUBSCRIBERS": 7610000,
    "VIEW_COUNT": 571518524,
    "VIDEO_COUNT": 1637,
    "SHARE_SUBSCRIBERS_PCT": "23.08",
    "SHARE_VIEWS_PCT": "14.70",
    "DELTA_SUBSCRIBERS_DOD": 10000
  },
  {
    "DT_SNAPSHOT": "2026-05-11",
    "CANAL_ID": "UCjt5Mt-yVu_R8LfuiLcd5KA",
    "CANAL_NOME": "Cafe com Ferri",
    "CANAL_HANDLE": "@podcastcafecomferri",
    "TIPO": "concorrente",
    "BU": "Redes Sociais",
    "SUBSCRIBERS": 6900000,
    "VIEW_COUNT": 157072359,
    "VIDEO_COUNT": 1270,
    "SHARE_SUBSCRIBERS_PCT": "20.93",
    "SHARE_VIEWS_PCT": "4.04",
    "DELTA_SUBSCRIBERS_DOD": 10000
  },
  {
    "DT_SNAPSHOT": "2026-05-11",
    "CANAL_ID": "UCCE-jo1GvBJqyj1b287h7jA",
    "CANAL_NOME": "Bruno Perini",
    "CANAL_HANDLE": "@brunoperini",
    "TIPO": "concorrente",
    "BU": "Redes Sociais",
    "SUBSCRIBERS": 2070000,
    "VIEW_COUNT": 472126454,
    "VIDEO_COUNT": 2352,
    "SHARE_SUBSCRIBERS_PCT": "6.28",
    "SHARE_VIEWS_PCT": "12.14",
    "DELTA_SUBSCRIBERS_DOD": 0
  },
  {
    "DT_SNAPSHOT": "2026-05-11",
    "CANAL_ID": "UCM3vJxmuJJkk1r0yzFI9eZg",
    "CANAL_NOME": "Investidor Sardinha",
    "CANAL_HANDLE": "@investidorsardinha",
    "TIPO": "concorrente",
    "BU": "Asset,Redes Sociais",
    "SUBSCRIBERS": 1640000,
    "VIEW_COUNT": 307135958,
    "VIDEO_COUNT": 3099,
    "SHARE_SUBSCRIBERS_PCT": "4.97",
    "SHARE_VIEWS_PCT": "7.90",
    "DELTA_SUBSCRIBERS_DOD": 0
  },
  {
    "DT_SNAPSHOT": "2026-05-11",
    "CANAL_ID": "UCE5Uu3nZlVbTur6xwhdoKhg",
    "CANAL_NOME": "BTG Pactual",
    "CANAL_HANDLE": "@btgpactual",
    "TIPO": "concorrente",
    "BU": "Redes Sociais",
    "SUBSCRIBERS": 1270000,
    "VIEW_COUNT": 219995422,
    "VIDEO_COUNT": 2838,
    "SHARE_SUBSCRIBERS_PCT": "3.85",
    "SHARE_VIEWS_PCT": "5.66",
    "DELTA_SUBSCRIBERS_DOD": 0
  },
  {
    "DT_SNAPSHOT": "2026-05-11",
    "CANAL_ID": "UCrp0zmecZ3TNV8FSR-tjv7A",
    "CANAL_NOME": "Economista Sincero",
    "CANAL_HANDLE": "@economistasincero",
    "TIPO": "concorrente",
    "BU": "Redes Sociais",
    "SUBSCRIBERS": 1270000,
    "VIEW_COUNT": 274551477,
    "VIDEO_COUNT": 4231,
    "SHARE_SUBSCRIBERS_PCT": "3.85",
    "SHARE_VIEWS_PCT": "7.06",
    "DELTA_SUBSCRIBERS_DOD": 0
  },
  {
    "DT_SNAPSHOT": "2026-05-11",
    "CANAL_ID": "UCu79AeVqrq42vmSIp1OHyfA",
    "CANAL_NOME": "Empiricus",
    "CANAL_HANDLE": "@empiricus",
    "TIPO": "concorrente",
    "BU": "Research",
    "SUBSCRIBERS": 1090000,
    "VIEW_COUNT": 98396240,
    "VIDEO_COUNT": 2444,
    "SHARE_SUBSCRIBERS_PCT": "3.31",
    "SHARE_VIEWS_PCT": "2.53",
    "DELTA_SUBSCRIBERS_DOD": 0
  },
  {
    "DT_SNAPSHOT": "2026-05-11",
    "CANAL_ID": "UCwONybZQdULFV_ts2911Rqg",
    "CANAL_NOME": "Tiago Reis (Suno)",
    "CANAL_HANDLE": "@tiagoreis",
    "TIPO": "proprio",
    "BU": "Research,Asset",
    "SUBSCRIBERS": 816000,
    "VIEW_COUNT": 117395049,
    "VIDEO_COUNT": 4383,
    "SHARE_SUBSCRIBERS_PCT": "2.48",
    "SHARE_VIEWS_PCT": "3.02",
    "DELTA_SUBSCRIBERS_DOD": 0
  },
  {
    "DT_SNAPSHOT": "2026-05-11",
    "CANAL_ID": "UCxm0tptjIc76-i26EKQ9NpA",
    "CANAL_NOME": "InfoMoney",
    "CANAL_HANDLE": "@infomoney",
    "TIPO": "concorrente",
    "BU": "Redes Sociais",
    "SUBSCRIBERS": 735000,
    "VIEW_COUNT": 157967004,
    "VIDEO_COUNT": 19030,
    "SHARE_SUBSCRIBERS_PCT": "2.23",
    "SHARE_VIEWS_PCT": "4.06",
    "DELTA_SUBSCRIBERS_DOD": 0
  },
  {
    "DT_SNAPSHOT": "2026-05-11",
    "CANAL_ID": "UCWDeEIDAIi_oYKDiqwfGyRg",
    "CANAL_NOME": "Suno Research",
    "CANAL_HANDLE": "@gruposuno",
    "TIPO": "proprio",
    "BU": "Research,Asset,Redes Sociais",
    "SUBSCRIBERS": 518000,
    "VIEW_COUNT": 108271695,
    "VIDEO_COUNT": 4688,
    "SHARE_SUBSCRIBERS_PCT": "1.57",
    "SHARE_VIEWS_PCT": "2.78",
    "DELTA_SUBSCRIBERS_DOD": 0
  },
  {
    "DT_SNAPSHOT": "2026-05-11",
    "CANAL_ID": "UCf15n72n6pV0RK6-GOi1s1Q",
    "CANAL_NOME": "XP Investimentos",
    "CANAL_HANDLE": "@xp_oficial",
    "TIPO": "concorrente",
    "BU": "Redes Sociais",
    "SUBSCRIBERS": 487000,
    "VIEW_COUNT": 710295275,
    "VIDEO_COUNT": 3894,
    "SHARE_SUBSCRIBERS_PCT": "1.48",
    "SHARE_VIEWS_PCT": "18.27",
    "DELTA_SUBSCRIBERS_DOD": 0
  },
  {
    "DT_SNAPSHOT": "2026-05-11",
    "CANAL_ID": "UCSXdP8V4jRaw-8YMTpa6glw",
    "CANAL_NOME": "Suno Baroni",
    "CANAL_HANDLE": "@professorbaroni",
    "TIPO": "proprio",
    "BU": "Asset,Redes Sociais",
    "SUBSCRIBERS": 349000,
    "VIEW_COUNT": 43036525,
    "VIDEO_COUNT": 3260,
    "SHARE_SUBSCRIBERS_PCT": "1.06",
    "SHARE_VIEWS_PCT": "1.11",
    "DELTA_SUBSCRIBERS_DOD": 0
  },
  {
    "DT_SNAPSHOT": "2026-05-11",
    "CANAL_ID": "UCsU0E4F3RxVOSjWlIMieReA",
    "CANAL_NOME": "Nord Investimentos",
    "CANAL_HANDLE": "@nordinvestimentos",
    "TIPO": "concorrente",
    "BU": "Research,Redes Sociais",
    "SUBSCRIBERS": 273000,
    "VIEW_COUNT": 20488183,
    "VIDEO_COUNT": 1227,
    "SHARE_SUBSCRIBERS_PCT": "0.83",
    "SHARE_VIEWS_PCT": "0.53",
    "DELTA_SUBSCRIBERS_DOD": 0
  },
  {
    "DT_SNAPSHOT": "2026-05-11",
    "CANAL_ID": "UC74FvQ6GtdwRmENGymLjqNA",
    "CANAL_NOME": "Suno Noticias",
    "CANAL_HANDLE": "@sunonoticias",
    "TIPO": "proprio",
    "BU": "Redes Sociais",
    "SUBSCRIBERS": 73800,
    "VIEW_COUNT": 8692358,
    "VIDEO_COUNT": 3412,
    "SHARE_SUBSCRIBERS_PCT": "0.22",
    "SHARE_VIEWS_PCT": "0.22",
    "DELTA_SUBSCRIBERS_DOD": 0
  },
  {
    "DT_SNAPSHOT": "2026-05-11",
    "CANAL_ID": "UCAbPPg9IVIjzPBAE7uGgd-g",
    "CANAL_NOME": "Funds Explorer",
    "CANAL_HANDLE": "@fundsexplorer",
    "TIPO": "proprio",
    "BU": "Asset",
    "SUBSCRIBERS": 67400,
    "VIEW_COUNT": 2692131,
    "VIDEO_COUNT": 653,
    "SHARE_SUBSCRIBERS_PCT": "0.20",
    "SHARE_VIEWS_PCT": "0.07",
    "DELTA_SUBSCRIBERS_DOD": 0
  },
  {
    "DT_SNAPSHOT": "2026-05-11",
    "CANAL_ID": "UC7k3dDEfclcB07Deoy41D6g",
    "CANAL_NOME": "Status Invest",
    "CANAL_HANDLE": "@statusinvest",
    "TIPO": "proprio",
    "BU": "Asset",
    "SUBSCRIBERS": 61600,
    "VIEW_COUNT": 3119063,
    "VIDEO_COUNT": 642,
    "SHARE_SUBSCRIBERS_PCT": "0.19",
    "SHARE_VIEWS_PCT": "0.08",
    "DELTA_SUBSCRIBERS_DOD": 0
  },
  {
    "DT_SNAPSHOT": "2026-05-11",
    "CANAL_ID": "UCMP3ETiqEPs0RMjxH57O5DQ",
    "CANAL_NOME": "Suno Asset",
    "CANAL_HANDLE": "@sunoasset",
    "TIPO": "proprio",
    "BU": "Asset",
    "SUBSCRIBERS": 8800,
    "VIEW_COUNT": 4784301,
    "VIDEO_COUNT": 637,
    "SHARE_SUBSCRIBERS_PCT": "0.03",
    "SHARE_VIEWS_PCT": "0.12",
    "DELTA_SUBSCRIBERS_DOD": 10
  },
  {
    "DT_SNAPSHOT": "2026-05-10",
    "CANAL_ID": "UC8mDF5mWNGE-Kpfcvnn0bUg",
    "CANAL_NOME": "Me Poupe!",
    "CANAL_HANDLE": "@mepoupe",
    "TIPO": "concorrente",
    "BU": "Redes Sociais",
    "SUBSCRIBERS": 7730000,
    "VIEW_COUNT": 610332026,
    "VIDEO_COUNT": 2339,
    "SHARE_SUBSCRIBERS_PCT": "23.46",
    "SHARE_VIEWS_PCT": "15.70",
    "DELTA_SUBSCRIBERS_DOD": 0
  },
  {
    "DT_SNAPSHOT": "2026-05-10",
    "CANAL_ID": "UCT4nDeU5pv1XIGySbSK-GgA",
    "CANAL_NOME": "O Primo Rico",
    "CANAL_HANDLE": "@primorico",
    "TIPO": "concorrente",
    "BU": "Redes Sociais",
    "SUBSCRIBERS": 7600000,
    "VIEW_COUNT": 571378668,
    "VIDEO_COUNT": 1636,
    "SHARE_SUBSCRIBERS_PCT": "23.07",
    "SHARE_VIEWS_PCT": "14.70",
    "DELTA_SUBSCRIBERS_DOD": 0
  },
  {
    "DT_SNAPSHOT": "2026-05-10",
    "CANAL_ID": "UCjt5Mt-yVu_R8LfuiLcd5KA",
    "CANAL_NOME": "Cafe com Ferri",
    "CANAL_HANDLE": "@podcastcafecomferri",
    "TIPO": "concorrente",
    "BU": "Redes Sociais",
    "SUBSCRIBERS": 6890000,
    "VIEW_COUNT": 156758332,
    "VIDEO_COUNT": 1268,
    "SHARE_SUBSCRIBERS_PCT": "20.91",
    "SHARE_VIEWS_PCT": "4.03",
    "DELTA_SUBSCRIBERS_DOD": 0
  },
  {
    "DT_SNAPSHOT": "2026-05-10",
    "CANAL_ID": "UCCE-jo1GvBJqyj1b287h7jA",
    "CANAL_NOME": "Bruno Perini",
    "CANAL_HANDLE": "@brunoperini",
    "TIPO": "concorrente",
    "BU": "Redes Sociais",
    "SUBSCRIBERS": 2070000,
    "VIEW_COUNT": 471897272,
    "VIDEO_COUNT": 2351,
    "SHARE_SUBSCRIBERS_PCT": "6.28",
    "SHARE_VIEWS_PCT": "12.14",
    "DELTA_SUBSCRIBERS_DOD": 0
  },
  {
    "DT_SNAPSHOT": "2026-05-10",
    "CANAL_ID": "UCM3vJxmuJJkk1r0yzFI9eZg",
    "CANAL_NOME": "Investidor Sardinha",
    "CANAL_HANDLE": "@investidorsardinha",
    "TIPO": "concorrente",
    "BU": "Asset,Redes Sociais",
    "SUBSCRIBERS": 1640000,
    "VIEW_COUNT": 307046955,
    "VIDEO_COUNT": 3098,
    "SHARE_SUBSCRIBERS_PCT": "4.98",
    "SHARE_VIEWS_PCT": "7.90",
    "DELTA_SUBSCRIBERS_DOD": 0
  },
  {
    "DT_SNAPSHOT": "2026-05-10",
    "CANAL_ID": "UCE5Uu3nZlVbTur6xwhdoKhg",
    "CANAL_NOME": "BTG Pactual",
    "CANAL_HANDLE": "@btgpactual",
    "TIPO": "concorrente",
    "BU": "Redes Sociais",
    "SUBSCRIBERS": 1270000,
    "VIEW_COUNT": 219848521,
    "VIDEO_COUNT": 2838,
    "SHARE_SUBSCRIBERS_PCT": "3.85",
    "SHARE_VIEWS_PCT": "5.66",
    "DELTA_SUBSCRIBERS_DOD": 10000
  },
  {
    "DT_SNAPSHOT": "2026-05-10",
    "CANAL_ID": "UCrp0zmecZ3TNV8FSR-tjv7A",
    "CANAL_NOME": "Economista Sincero",
    "CANAL_HANDLE": "@economistasincero",
    "TIPO": "concorrente",
    "BU": "Redes Sociais",
    "SUBSCRIBERS": 1270000,
    "VIEW_COUNT": 274441364,
    "VIDEO_COUNT": 4230,
    "SHARE_SUBSCRIBERS_PCT": "3.85",
    "SHARE_VIEWS_PCT": "7.06",
    "DELTA_SUBSCRIBERS_DOD": 0
  },
  {
    "DT_SNAPSHOT": "2026-05-10",
    "CANAL_ID": "UCu79AeVqrq42vmSIp1OHyfA",
    "CANAL_NOME": "Empiricus",
    "CANAL_HANDLE": "@empiricus",
    "TIPO": "concorrente",
    "BU": "Research",
    "SUBSCRIBERS": 1090000,
    "VIEW_COUNT": 98374720,
    "VIDEO_COUNT": 2444,
    "SHARE_SUBSCRIBERS_PCT": "3.31",
    "SHARE_VIEWS_PCT": "2.53",
    "DELTA_SUBSCRIBERS_DOD": 0
  },
  {
    "DT_SNAPSHOT": "2026-05-10",
    "CANAL_ID": "UCwONybZQdULFV_ts2911Rqg",
    "CANAL_NOME": "Tiago Reis (Suno)",
    "CANAL_HANDLE": "@tiagoreis",
    "TIPO": "proprio",
    "BU": "Research,Asset",
    "SUBSCRIBERS": 816000,
    "VIEW_COUNT": 117387414,
    "VIDEO_COUNT": 4383,
    "SHARE_SUBSCRIBERS_PCT": "2.48",
    "SHARE_VIEWS_PCT": "3.02",
    "DELTA_SUBSCRIBERS_DOD": 0
  },
  {
    "DT_SNAPSHOT": "2026-05-10",
    "CANAL_ID": "UCxm0tptjIc76-i26EKQ9NpA",
    "CANAL_NOME": "InfoMoney",
    "CANAL_HANDLE": "@infomoney",
    "TIPO": "concorrente",
    "BU": "Redes Sociais",
    "SUBSCRIBERS": 735000,
    "VIEW_COUNT": 157708484,
    "VIDEO_COUNT": 19012,
    "SHARE_SUBSCRIBERS_PCT": "2.23",
    "SHARE_VIEWS_PCT": "4.06",
    "DELTA_SUBSCRIBERS_DOD": 0
  },
  {
    "DT_SNAPSHOT": "2026-05-10",
    "CANAL_ID": "UCWDeEIDAIi_oYKDiqwfGyRg",
    "CANAL_NOME": "Suno Research",
    "CANAL_HANDLE": "@gruposuno",
    "TIPO": "proprio",
    "BU": "Research,Asset,Redes Sociais",
    "SUBSCRIBERS": 518000,
    "VIEW_COUNT": 108265580,
    "VIDEO_COUNT": 4687,
    "SHARE_SUBSCRIBERS_PCT": "1.57",
    "SHARE_VIEWS_PCT": "2.79",
    "DELTA_SUBSCRIBERS_DOD": 0
  },
  {
    "DT_SNAPSHOT": "2026-05-10",
    "CANAL_ID": "UCf15n72n6pV0RK6-GOi1s1Q",
    "CANAL_NOME": "XP Investimentos",
    "CANAL_HANDLE": "@xp_oficial",
    "TIPO": "concorrente",
    "BU": "Redes Sociais",
    "SUBSCRIBERS": 487000,
    "VIEW_COUNT": 710294133,
    "VIDEO_COUNT": 3894,
    "SHARE_SUBSCRIBERS_PCT": "1.48",
    "SHARE_VIEWS_PCT": "18.28",
    "DELTA_SUBSCRIBERS_DOD": 0
  },
  {
    "DT_SNAPSHOT": "2026-05-10",
    "CANAL_ID": "UCSXdP8V4jRaw-8YMTpa6glw",
    "CANAL_NOME": "Suno Baroni",
    "CANAL_HANDLE": "@professorbaroni",
    "TIPO": "proprio",
    "BU": "Asset,Redes Sociais",
    "SUBSCRIBERS": 349000,
    "VIEW_COUNT": 43032631,
    "VIDEO_COUNT": 3258,
    "SHARE_SUBSCRIBERS_PCT": "1.06",
    "SHARE_VIEWS_PCT": "1.11",
    "DELTA_SUBSCRIBERS_DOD": 0
  },
  {
    "DT_SNAPSHOT": "2026-05-10",
    "CANAL_ID": "UCsU0E4F3RxVOSjWlIMieReA",
    "CANAL_NOME": "Nord Investimentos",
    "CANAL_HANDLE": "@nordinvestimentos",
    "TIPO": "concorrente",
    "BU": "Research,Redes Sociais",
    "SUBSCRIBERS": 273000,
    "VIEW_COUNT": 20481619,
    "VIDEO_COUNT": 1227,
    "SHARE_SUBSCRIBERS_PCT": "0.83",
    "SHARE_VIEWS_PCT": "0.53",
    "DELTA_SUBSCRIBERS_DOD": 0
  },
  {
    "DT_SNAPSHOT": "2026-05-10",
    "CANAL_ID": "UC74FvQ6GtdwRmENGymLjqNA",
    "CANAL_NOME": "Suno Noticias",
    "CANAL_HANDLE": "@sunonoticias",
    "TIPO": "proprio",
    "BU": "Redes Sociais",
    "SUBSCRIBERS": 73800,
    "VIEW_COUNT": 8692038,
    "VIDEO_COUNT": 3412,
    "SHARE_SUBSCRIBERS_PCT": "0.22",
    "SHARE_VIEWS_PCT": "0.22",
    "DELTA_SUBSCRIBERS_DOD": 0
  },
  {
    "DT_SNAPSHOT": "2026-05-10",
    "CANAL_ID": "UCAbPPg9IVIjzPBAE7uGgd-g",
    "CANAL_NOME": "Funds Explorer",
    "CANAL_HANDLE": "@fundsexplorer",
    "TIPO": "proprio",
    "BU": "Asset",
    "SUBSCRIBERS": 67400,
    "VIEW_COUNT": 2690729,
    "VIDEO_COUNT": 653,
    "SHARE_SUBSCRIBERS_PCT": "0.20",
    "SHARE_VIEWS_PCT": "0.07",
    "DELTA_SUBSCRIBERS_DOD": 0
  },
  {
    "DT_SNAPSHOT": "2026-05-10",
    "CANAL_ID": "UC7k3dDEfclcB07Deoy41D6g",
    "CANAL_NOME": "Status Invest",
    "CANAL_HANDLE": "@statusinvest",
    "TIPO": "proprio",
    "BU": "Asset",
    "SUBSCRIBERS": 61600,
    "VIEW_COUNT": 3118023,
    "VIDEO_COUNT": 642,
    "SHARE_SUBSCRIBERS_PCT": "0.19",
    "SHARE_VIEWS_PCT": "0.08",
    "DELTA_SUBSCRIBERS_DOD": 0
  },
  {
    "DT_SNAPSHOT": "2026-05-10",
    "CANAL_ID": "UCMP3ETiqEPs0RMjxH57O5DQ",
    "CANAL_NOME": "Suno Asset",
    "CANAL_HANDLE": "@sunoasset",
    "TIPO": "proprio",
    "BU": "Asset",
    "SUBSCRIBERS": 8790,
    "VIEW_COUNT": 4776359,
    "VIDEO_COUNT": 637,
    "SHARE_SUBSCRIBERS_PCT": "0.03",
    "SHARE_VIEWS_PCT": "0.12",
    "DELTA_SUBSCRIBERS_DOD": 0
  },
  {
    "DT_SNAPSHOT": "2026-05-09",
    "CANAL_ID": "UC8mDF5mWNGE-Kpfcvnn0bUg",
    "CANAL_NOME": "Me Poupe!",
    "CANAL_HANDLE": "@mepoupe",
    "TIPO": "concorrente",
    "BU": "Redes Sociais",
    "SUBSCRIBERS": 7730000,
    "VIEW_COUNT": 610187990,
    "VIDEO_COUNT": 2337,
    "SHARE_SUBSCRIBERS_PCT": "23.47",
    "SHARE_VIEWS_PCT": "15.71",
    "DELTA_SUBSCRIBERS_DOD": 0
  },
  {
    "DT_SNAPSHOT": "2026-05-09",
    "CANAL_ID": "UCT4nDeU5pv1XIGySbSK-GgA",
    "CANAL_NOME": "O Primo Rico",
    "CANAL_HANDLE": "@primorico",
    "TIPO": "concorrente",
    "BU": "Redes Sociais",
    "SUBSCRIBERS": 7600000,
    "VIEW_COUNT": 571146092,
    "VIDEO_COUNT": 1636,
    "SHARE_SUBSCRIBERS_PCT": "23.07",
    "SHARE_VIEWS_PCT": "14.70",
    "DELTA_SUBSCRIBERS_DOD": 0
  },
  {
    "DT_SNAPSHOT": "2026-05-09",
    "CANAL_ID": "UCjt5Mt-yVu_R8LfuiLcd5KA",
    "CANAL_NOME": "Cafe com Ferri",
    "CANAL_HANDLE": "@podcastcafecomferri",
    "TIPO": "concorrente",
    "BU": "Redes Sociais",
    "SUBSCRIBERS": 6890000,
    "VIEW_COUNT": 156367448,
    "VIDEO_COUNT": 1266,
    "SHARE_SUBSCRIBERS_PCT": "20.92",
    "SHARE_VIEWS_PCT": "4.03",
    "DELTA_SUBSCRIBERS_DOD": 10000
  },
  {
    "DT_SNAPSHOT": "2026-05-09",
    "CANAL_ID": "UCCE-jo1GvBJqyj1b287h7jA",
    "CANAL_NOME": "Bruno Perini",
    "CANAL_HANDLE": "@brunoperini",
    "TIPO": "concorrente",
    "BU": "Redes Sociais",
    "SUBSCRIBERS": 2070000,
    "VIEW_COUNT": 471696359,
    "VIDEO_COUNT": 2350,
    "SHARE_SUBSCRIBERS_PCT": "6.28",
    "SHARE_VIEWS_PCT": "12.14",
    "DELTA_SUBSCRIBERS_DOD": 0
  },
  {
    "DT_SNAPSHOT": "2026-05-09",
    "CANAL_ID": "UCM3vJxmuJJkk1r0yzFI9eZg",
    "CANAL_NOME": "Investidor Sardinha",
    "CANAL_HANDLE": "@investidorsardinha",
    "TIPO": "concorrente",
    "BU": "Asset,Redes Sociais",
    "SUBSCRIBERS": 1640000,
    "VIEW_COUNT": 306794792,
    "VIDEO_COUNT": 3097,
    "SHARE_SUBSCRIBERS_PCT": "4.98",
    "SHARE_VIEWS_PCT": "7.90",
    "DELTA_SUBSCRIBERS_DOD": 0
  },
  {
    "DT_SNAPSHOT": "2026-05-09",
    "CANAL_ID": "UCrp0zmecZ3TNV8FSR-tjv7A",
    "CANAL_NOME": "Economista Sincero",
    "CANAL_HANDLE": "@economistasincero",
    "TIPO": "concorrente",
    "BU": "Redes Sociais",
    "SUBSCRIBERS": 1270000,
    "VIEW_COUNT": 274353772,
    "VIDEO_COUNT": 4227,
    "SHARE_SUBSCRIBERS_PCT": "3.86",
    "SHARE_VIEWS_PCT": "7.06",
    "DELTA_SUBSCRIBERS_DOD": 0
  },
  {
    "DT_SNAPSHOT": "2026-05-09",
    "CANAL_ID": "UCE5Uu3nZlVbTur6xwhdoKhg",
    "CANAL_NOME": "BTG Pactual",
    "CANAL_HANDLE": "@btgpactual",
    "TIPO": "concorrente",
    "BU": "Redes Sociais",
    "SUBSCRIBERS": 1260000,
    "VIEW_COUNT": 219674189,
    "VIDEO_COUNT": 2838,
    "SHARE_SUBSCRIBERS_PCT": "3.83",
    "SHARE_VIEWS_PCT": "5.66",
    "DELTA_SUBSCRIBERS_DOD": 0
  },
  {
    "DT_SNAPSHOT": "2026-05-09",
    "CANAL_ID": "UCu79AeVqrq42vmSIp1OHyfA",
    "CANAL_NOME": "Empiricus",
    "CANAL_HANDLE": "@empiricus",
    "TIPO": "concorrente",
    "BU": "Research",
    "SUBSCRIBERS": 1090000,
    "VIEW_COUNT": 98348337,
    "VIDEO_COUNT": 2445,
    "SHARE_SUBSCRIBERS_PCT": "3.31",
    "SHARE_VIEWS_PCT": "2.53",
    "DELTA_SUBSCRIBERS_DOD": 0
  },
  {
    "DT_SNAPSHOT": "2026-05-09",
    "CANAL_ID": "UCwONybZQdULFV_ts2911Rqg",
    "CANAL_NOME": "Tiago Reis (Suno)",
    "CANAL_HANDLE": "@tiagoreis",
    "TIPO": "proprio",
    "BU": "Research,Asset",
    "SUBSCRIBERS": 816000,
    "VIEW_COUNT": 117356020,
    "VIDEO_COUNT": 4383,
    "SHARE_SUBSCRIBERS_PCT": "2.48",
    "SHARE_VIEWS_PCT": "3.02",
    "DELTA_SUBSCRIBERS_DOD": 0
  },
  {
    "DT_SNAPSHOT": "2026-05-09",
    "CANAL_ID": "UCxm0tptjIc76-i26EKQ9NpA",
    "CANAL_NOME": "InfoMoney",
    "CANAL_HANDLE": "@infomoney",
    "TIPO": "concorrente",
    "BU": "Redes Sociais",
    "SUBSCRIBERS": 735000,
    "VIEW_COUNT": 157322783,
    "VIDEO_COUNT": 18990,
    "SHARE_SUBSCRIBERS_PCT": "2.23",
    "SHARE_VIEWS_PCT": "4.05",
    "DELTA_SUBSCRIBERS_DOD": 1000
  },
  {
    "DT_SNAPSHOT": "2026-05-09",
    "CANAL_ID": "UCWDeEIDAIi_oYKDiqwfGyRg",
    "CANAL_NOME": "Suno Research",
    "CANAL_HANDLE": "@gruposuno",
    "TIPO": "proprio",
    "BU": "Research,Asset,Redes Sociais",
    "SUBSCRIBERS": 518000,
    "VIEW_COUNT": 108253906,
    "VIDEO_COUNT": 4686,
    "SHARE_SUBSCRIBERS_PCT": "1.57",
    "SHARE_VIEWS_PCT": "2.79",
    "DELTA_SUBSCRIBERS_DOD": 0
  },
  {
    "DT_SNAPSHOT": "2026-05-09",
    "CANAL_ID": "UCf15n72n6pV0RK6-GOi1s1Q",
    "CANAL_NOME": "XP Investimentos",
    "CANAL_HANDLE": "@xp_oficial",
    "TIPO": "concorrente",
    "BU": "Redes Sociais",
    "SUBSCRIBERS": 487000,
    "VIEW_COUNT": 710289201,
    "VIDEO_COUNT": 3893,
    "SHARE_SUBSCRIBERS_PCT": "1.48",
    "SHARE_VIEWS_PCT": "18.28",
    "DELTA_SUBSCRIBERS_DOD": 0
  },
  {
    "DT_SNAPSHOT": "2026-05-09",
    "CANAL_ID": "UCSXdP8V4jRaw-8YMTpa6glw",
    "CANAL_NOME": "Suno Baroni",
    "CANAL_HANDLE": "@professorbaroni",
    "TIPO": "proprio",
    "BU": "Asset,Redes Sociais",
    "SUBSCRIBERS": 349000,
    "VIEW_COUNT": 43020364,
    "VIDEO_COUNT": 3256,
    "SHARE_SUBSCRIBERS_PCT": "1.06",
    "SHARE_VIEWS_PCT": "1.11",
    "DELTA_SUBSCRIBERS_DOD": 0
  },
  {
    "DT_SNAPSHOT": "2026-05-09",
    "CANAL_ID": "UCsU0E4F3RxVOSjWlIMieReA",
    "CANAL_NOME": "Nord Investimentos",
    "CANAL_HANDLE": "@nordinvestimentos",
    "TIPO": "concorrente",
    "BU": "Research,Redes Sociais",
    "SUBSCRIBERS": 273000,
    "VIEW_COUNT": 20474763,
    "VIDEO_COUNT": 1226,
    "SHARE_SUBSCRIBERS_PCT": "0.83",
    "SHARE_VIEWS_PCT": "0.53",
    "DELTA_SUBSCRIBERS_DOD": 0
  },
  {
    "DT_SNAPSHOT": "2026-05-09",
    "CANAL_ID": "UC74FvQ6GtdwRmENGymLjqNA",
    "CANAL_NOME": "Suno Noticias",
    "CANAL_HANDLE": "@sunonoticias",
    "TIPO": "proprio",
    "BU": "Redes Sociais",
    "SUBSCRIBERS": 73800,
    "VIEW_COUNT": 8691712,
    "VIDEO_COUNT": 3412,
    "SHARE_SUBSCRIBERS_PCT": "0.22",
    "SHARE_VIEWS_PCT": "0.22",
    "DELTA_SUBSCRIBERS_DOD": 0
  },
  {
    "DT_SNAPSHOT": "2026-05-09",
    "CANAL_ID": "UCAbPPg9IVIjzPBAE7uGgd-g",
    "CANAL_NOME": "Funds Explorer",
    "CANAL_HANDLE": "@fundsexplorer",
    "TIPO": "proprio",
    "BU": "Asset",
    "SUBSCRIBERS": 67400,
    "VIEW_COUNT": 2689821,
    "VIDEO_COUNT": 652,
    "SHARE_SUBSCRIBERS_PCT": "0.20",
    "SHARE_VIEWS_PCT": "0.07",
    "DELTA_SUBSCRIBERS_DOD": 0
  },
  {
    "DT_SNAPSHOT": "2026-05-09",
    "CANAL_ID": "UC7k3dDEfclcB07Deoy41D6g",
    "CANAL_NOME": "Status Invest",
    "CANAL_HANDLE": "@statusinvest",
    "TIPO": "proprio",
    "BU": "Asset",
    "SUBSCRIBERS": 61600,
    "VIEW_COUNT": 3117004,
    "VIDEO_COUNT": 642,
    "SHARE_SUBSCRIBERS_PCT": "0.19",
    "SHARE_VIEWS_PCT": "0.08",
    "DELTA_SUBSCRIBERS_DOD": 0
  },
  {
    "DT_SNAPSHOT": "2026-05-09",
    "CANAL_ID": "UCMP3ETiqEPs0RMjxH57O5DQ",
    "CANAL_NOME": "Suno Asset",
    "CANAL_HANDLE": "@sunoasset",
    "TIPO": "proprio",
    "BU": "Asset",
    "SUBSCRIBERS": 8790,
    "VIEW_COUNT": 4770239,
    "VIDEO_COUNT": 637,
    "SHARE_SUBSCRIBERS_PCT": "0.03",
    "SHARE_VIEWS_PCT": "0.12",
    "DELTA_SUBSCRIBERS_DOD": 10
  },
  {
    "DT_SNAPSHOT": "2026-05-08",
    "CANAL_ID": "UC8mDF5mWNGE-Kpfcvnn0bUg",
    "CANAL_NOME": "Me Poupe!",
    "CANAL_HANDLE": "@mepoupe",
    "TIPO": "concorrente",
    "BU": "Redes Sociais",
    "SUBSCRIBERS": 7730000,
    "VIEW_COUNT": 610078458,
    "VIDEO_COUNT": 2335,
    "SHARE_SUBSCRIBERS_PCT": "23.48",
    "SHARE_VIEWS_PCT": "15.71",
    "DELTA_SUBSCRIBERS_DOD": 0
  },
  {
    "DT_SNAPSHOT": "2026-05-08",
    "CANAL_ID": "UCT4nDeU5pv1XIGySbSK-GgA",
    "CANAL_NOME": "O Primo Rico",
    "CANAL_HANDLE": "@primorico",
    "TIPO": "concorrente",
    "BU": "Redes Sociais",
    "SUBSCRIBERS": 7600000,
    "VIEW_COUNT": 570933069,
    "VIDEO_COUNT": 1634,
    "SHARE_SUBSCRIBERS_PCT": "23.08",
    "SHARE_VIEWS_PCT": "14.70",
    "DELTA_SUBSCRIBERS_DOD": 0
  },
  {
    "DT_SNAPSHOT": "2026-05-08",
    "CANAL_ID": "UCjt5Mt-yVu_R8LfuiLcd5KA",
    "CANAL_NOME": "Cafe com Ferri",
    "CANAL_HANDLE": "@podcastcafecomferri",
    "TIPO": "concorrente",
    "BU": "Redes Sociais",
    "SUBSCRIBERS": 6880000,
    "VIEW_COUNT": 155986035,
    "VIDEO_COUNT": 1261,
    "SHARE_SUBSCRIBERS_PCT": "20.89",
    "SHARE_VIEWS_PCT": "4.02",
    "DELTA_SUBSCRIBERS_DOD": 0
  },
  {
    "DT_SNAPSHOT": "2026-05-08",
    "CANAL_ID": "UCCE-jo1GvBJqyj1b287h7jA",
    "CANAL_NOME": "Bruno Perini",
    "CANAL_HANDLE": "@brunoperini",
    "TIPO": "concorrente",
    "BU": "Redes Sociais",
    "SUBSCRIBERS": 2070000,
    "VIEW_COUNT": 471544045,
    "VIDEO_COUNT": 2349,
    "SHARE_SUBSCRIBERS_PCT": "6.29",
    "SHARE_VIEWS_PCT": "12.14",
    "DELTA_SUBSCRIBERS_DOD": 0
  },
  {
    "DT_SNAPSHOT": "2026-05-08",
    "CANAL_ID": "UCM3vJxmuJJkk1r0yzFI9eZg",
    "CANAL_NOME": "Investidor Sardinha",
    "CANAL_HANDLE": "@investidorsardinha",
    "TIPO": "concorrente",
    "BU": "Asset,Redes Sociais",
    "SUBSCRIBERS": 1640000,
    "VIEW_COUNT": 306551209,
    "VIDEO_COUNT": 3096,
    "SHARE_SUBSCRIBERS_PCT": "4.98",
    "SHARE_VIEWS_PCT": "7.89",
    "DELTA_SUBSCRIBERS_DOD": 0
  },
  {
    "DT_SNAPSHOT": "2026-05-08",
    "CANAL_ID": "UCrp0zmecZ3TNV8FSR-tjv7A",
    "CANAL_NOME": "Economista Sincero",
    "CANAL_HANDLE": "@economistasincero",
    "TIPO": "concorrente",
    "BU": "Redes Sociais",
    "SUBSCRIBERS": 1270000,
    "VIEW_COUNT": 274246657,
    "VIDEO_COUNT": 4224,
    "SHARE_SUBSCRIBERS_PCT": "3.86",
    "SHARE_VIEWS_PCT": "7.06",
    "DELTA_SUBSCRIBERS_DOD": 0
  },
  {
    "DT_SNAPSHOT": "2026-05-08",
    "CANAL_ID": "UCE5Uu3nZlVbTur6xwhdoKhg",
    "CANAL_NOME": "BTG Pactual",
    "CANAL_HANDLE": "@btgpactual",
    "TIPO": "concorrente",
    "BU": "Redes Sociais",
    "SUBSCRIBERS": 1260000,
    "VIEW_COUNT": 219539162,
    "VIDEO_COUNT": 2836,
    "SHARE_SUBSCRIBERS_PCT": "3.83",
    "SHARE_VIEWS_PCT": "5.65",
    "DELTA_SUBSCRIBERS_DOD": 0
  },
  {
    "DT_SNAPSHOT": "2026-05-08",
    "CANAL_ID": "UCu79AeVqrq42vmSIp1OHyfA",
    "CANAL_NOME": "Empiricus",
    "CANAL_HANDLE": "@empiricus",
    "TIPO": "concorrente",
    "BU": "Research",
    "SUBSCRIBERS": 1090000,
    "VIEW_COUNT": 98334576,
    "VIDEO_COUNT": 2438,
    "SHARE_SUBSCRIBERS_PCT": "3.31",
    "SHARE_VIEWS_PCT": "2.53",
    "DELTA_SUBSCRIBERS_DOD": 0
  },
  {
    "DT_SNAPSHOT": "2026-05-08",
    "CANAL_ID": "UCwONybZQdULFV_ts2911Rqg",
    "CANAL_NOME": "Tiago Reis (Suno)",
    "CANAL_HANDLE": "@tiagoreis",
    "TIPO": "proprio",
    "BU": "Research,Asset",
    "SUBSCRIBERS": 816000,
    "VIEW_COUNT": 117317071,
    "VIDEO_COUNT": 4383,
    "SHARE_SUBSCRIBERS_PCT": "2.48",
    "SHARE_VIEWS_PCT": "3.02",
    "DELTA_SUBSCRIBERS_DOD": 0
  },
  {
    "DT_SNAPSHOT": "2026-05-08",
    "CANAL_ID": "UCxm0tptjIc76-i26EKQ9NpA",
    "CANAL_NOME": "InfoMoney",
    "CANAL_HANDLE": "@infomoney",
    "TIPO": "concorrente",
    "BU": "Redes Sociais",
    "SUBSCRIBERS": 734000,
    "VIEW_COUNT": 157091900,
    "VIDEO_COUNT": 18963,
    "SHARE_SUBSCRIBERS_PCT": "2.23",
    "SHARE_VIEWS_PCT": "4.05",
    "DELTA_SUBSCRIBERS_DOD": 0
  },
  {
    "DT_SNAPSHOT": "2026-05-08",
    "CANAL_ID": "UCWDeEIDAIi_oYKDiqwfGyRg",
    "CANAL_NOME": "Suno Research",
    "CANAL_HANDLE": "@gruposuno",
    "TIPO": "proprio",
    "BU": "Research,Asset,Redes Sociais",
    "SUBSCRIBERS": 518000,
    "VIEW_COUNT": 108241815,
    "VIDEO_COUNT": 4684,
    "SHARE_SUBSCRIBERS_PCT": "1.57",
    "SHARE_VIEWS_PCT": "2.79",
    "DELTA_SUBSCRIBERS_DOD": 0
  },
  {
    "DT_SNAPSHOT": "2026-05-08",
    "CANAL_ID": "UCf15n72n6pV0RK6-GOi1s1Q",
    "CANAL_NOME": "XP Investimentos",
    "CANAL_HANDLE": "@xp_oficial",
    "TIPO": "concorrente",
    "BU": "Redes Sociais",
    "SUBSCRIBERS": 487000,
    "VIEW_COUNT": 710278655,
    "VIDEO_COUNT": 3891,
    "SHARE_SUBSCRIBERS_PCT": "1.48",
    "SHARE_VIEWS_PCT": "18.29",
    "DELTA_SUBSCRIBERS_DOD": 0
  },
  {
    "DT_SNAPSHOT": "2026-05-08",
    "CANAL_ID": "UCSXdP8V4jRaw-8YMTpa6glw",
    "CANAL_NOME": "Suno Baroni",
    "CANAL_HANDLE": "@professorbaroni",
    "TIPO": "proprio",
    "BU": "Asset,Redes Sociais",
    "SUBSCRIBERS": 349000,
    "VIEW_COUNT": 42996560,
    "VIDEO_COUNT": 3255,
    "SHARE_SUBSCRIBERS_PCT": "1.06",
    "SHARE_VIEWS_PCT": "1.11",
    "DELTA_SUBSCRIBERS_DOD": 0
  },
  {
    "DT_SNAPSHOT": "2026-05-08",
    "CANAL_ID": "UCsU0E4F3RxVOSjWlIMieReA",
    "CANAL_NOME": "Nord Investimentos",
    "CANAL_HANDLE": "@nordinvestimentos",
    "TIPO": "concorrente",
    "BU": "Research,Redes Sociais",
    "SUBSCRIBERS": 273000,
    "VIEW_COUNT": 20472514,
    "VIDEO_COUNT": 1226,
    "SHARE_SUBSCRIBERS_PCT": "0.83",
    "SHARE_VIEWS_PCT": "0.53",
    "DELTA_SUBSCRIBERS_DOD": 0
  },
  {
    "DT_SNAPSHOT": "2026-05-08",
    "CANAL_ID": "UC74FvQ6GtdwRmENGymLjqNA",
    "CANAL_NOME": "Suno Noticias",
    "CANAL_HANDLE": "@sunonoticias",
    "TIPO": "proprio",
    "BU": "Redes Sociais",
    "SUBSCRIBERS": 73800,
    "VIEW_COUNT": 8691376,
    "VIDEO_COUNT": 3412,
    "SHARE_SUBSCRIBERS_PCT": "0.22",
    "SHARE_VIEWS_PCT": "0.22",
    "DELTA_SUBSCRIBERS_DOD": 0
  },
  {
    "DT_SNAPSHOT": "2026-05-08",
    "CANAL_ID": "UCAbPPg9IVIjzPBAE7uGgd-g",
    "CANAL_NOME": "Funds Explorer",
    "CANAL_HANDLE": "@fundsexplorer",
    "TIPO": "proprio",
    "BU": "Asset",
    "SUBSCRIBERS": 67400,
    "VIEW_COUNT": 2687628,
    "VIDEO_COUNT": 651,
    "SHARE_SUBSCRIBERS_PCT": "0.20",
    "SHARE_VIEWS_PCT": "0.07",
    "DELTA_SUBSCRIBERS_DOD": 0
  },
  {
    "DT_SNAPSHOT": "2026-05-08",
    "CANAL_ID": "UC7k3dDEfclcB07Deoy41D6g",
    "CANAL_NOME": "Status Invest",
    "CANAL_HANDLE": "@statusinvest",
    "TIPO": "proprio",
    "BU": "Asset",
    "SUBSCRIBERS": 61600,
    "VIEW_COUNT": 3116289,
    "VIDEO_COUNT": 642,
    "SHARE_SUBSCRIBERS_PCT": "0.19",
    "SHARE_VIEWS_PCT": "0.08",
    "DELTA_SUBSCRIBERS_DOD": 0
  },
  {
    "DT_SNAPSHOT": "2026-05-08",
    "CANAL_ID": "UCMP3ETiqEPs0RMjxH57O5DQ",
    "CANAL_NOME": "Suno Asset",
    "CANAL_HANDLE": "@sunoasset",
    "TIPO": "proprio",
    "BU": "Asset",
    "SUBSCRIBERS": 8780,
    "VIEW_COUNT": 4765489,
    "VIDEO_COUNT": 637,
    "SHARE_SUBSCRIBERS_PCT": "0.03",
    "SHARE_VIEWS_PCT": "0.12",
    "DELTA_SUBSCRIBERS_DOD": 10
  },
  {
    "DT_SNAPSHOT": "2026-05-07",
    "CANAL_ID": "UC8mDF5mWNGE-Kpfcvnn0bUg",
    "CANAL_NOME": "Me Poupe!",
    "CANAL_HANDLE": "@mepoupe",
    "TIPO": "concorrente",
    "BU": "Redes Sociais",
    "SUBSCRIBERS": 7730000,
    "VIEW_COUNT": 609968930,
    "VIDEO_COUNT": 2332,
    "SHARE_SUBSCRIBERS_PCT": "23.48",
    "SHARE_VIEWS_PCT": "15.71",
    "DELTA_SUBSCRIBERS_DOD": 0
  },
  {
    "DT_SNAPSHOT": "2026-05-07",
    "CANAL_ID": "UCT4nDeU5pv1XIGySbSK-GgA",
    "CANAL_NOME": "O Primo Rico",
    "CANAL_HANDLE": "@primorico",
    "TIPO": "concorrente",
    "BU": "Redes Sociais",
    "SUBSCRIBERS": 7600000,
    "VIEW_COUNT": 570675783,
    "VIDEO_COUNT": 1633,
    "SHARE_SUBSCRIBERS_PCT": "23.08",
    "SHARE_VIEWS_PCT": "14.70",
    "DELTA_SUBSCRIBERS_DOD": 0
  },
  {
    "DT_SNAPSHOT": "2026-05-07",
    "CANAL_ID": "UCjt5Mt-yVu_R8LfuiLcd5KA",
    "CANAL_NOME": "Cafe com Ferri",
    "CANAL_HANDLE": "@podcastcafecomferri",
    "TIPO": "concorrente",
    "BU": "Redes Sociais",
    "SUBSCRIBERS": 6880000,
    "VIEW_COUNT": 155681054,
    "VIDEO_COUNT": 1261,
    "SHARE_SUBSCRIBERS_PCT": "20.89",
    "SHARE_VIEWS_PCT": "4.01",
    "DELTA_SUBSCRIBERS_DOD": 10000
  },
  {
    "DT_SNAPSHOT": "2026-05-07",
    "CANAL_ID": "UCCE-jo1GvBJqyj1b287h7jA",
    "CANAL_NOME": "Bruno Perini",
    "CANAL_HANDLE": "@brunoperini",
    "TIPO": "concorrente",
    "BU": "Redes Sociais",
    "SUBSCRIBERS": 2070000,
    "VIEW_COUNT": 471607346,
    "VIDEO_COUNT": 2351,
    "SHARE_SUBSCRIBERS_PCT": "6.29",
    "SHARE_VIEWS_PCT": "12.15",
    "DELTA_SUBSCRIBERS_DOD": 0
  },
  {
    "DT_SNAPSHOT": "2026-05-07",
    "CANAL_ID": "UCM3vJxmuJJkk1r0yzFI9eZg",
    "CANAL_NOME": "Investidor Sardinha",
    "CANAL_HANDLE": "@investidorsardinha",
    "TIPO": "concorrente",
    "BU": "Asset,Redes Sociais",
    "SUBSCRIBERS": 1640000,
    "VIEW_COUNT": 306296899,
    "VIDEO_COUNT": 3095,
    "SHARE_SUBSCRIBERS_PCT": "4.98",
    "SHARE_VIEWS_PCT": "7.89",
    "DELTA_SUBSCRIBERS_DOD": 0
  },
  {
    "DT_SNAPSHOT": "2026-05-07",
    "CANAL_ID": "UCrp0zmecZ3TNV8FSR-tjv7A",
    "CANAL_NOME": "Economista Sincero",
    "CANAL_HANDLE": "@economistasincero",
    "TIPO": "concorrente",
    "BU": "Redes Sociais",
    "SUBSCRIBERS": 1270000,
    "VIEW_COUNT": 274166590,
    "VIDEO_COUNT": 4220,
    "SHARE_SUBSCRIBERS_PCT": "3.86",
    "SHARE_VIEWS_PCT": "7.06",
    "DELTA_SUBSCRIBERS_DOD": 0
  },
  {
    "DT_SNAPSHOT": "2026-05-07",
    "CANAL_ID": "UCE5Uu3nZlVbTur6xwhdoKhg",
    "CANAL_NOME": "BTG Pactual",
    "CANAL_HANDLE": "@btgpactual",
    "TIPO": "concorrente",
    "BU": "Redes Sociais",
    "SUBSCRIBERS": 1260000,
    "VIEW_COUNT": 219406816,
    "VIDEO_COUNT": 2832,
    "SHARE_SUBSCRIBERS_PCT": "3.83",
    "SHARE_VIEWS_PCT": "5.65",
    "DELTA_SUBSCRIBERS_DOD": 0
  },
  {
    "DT_SNAPSHOT": "2026-05-07",
    "CANAL_ID": "UCu79AeVqrq42vmSIp1OHyfA",
    "CANAL_NOME": "Empiricus",
    "CANAL_HANDLE": "@empiricus",
    "TIPO": "concorrente",
    "BU": "Research",
    "SUBSCRIBERS": 1090000,
    "VIEW_COUNT": 98332464,
    "VIDEO_COUNT": 2434,
    "SHARE_SUBSCRIBERS_PCT": "3.31",
    "SHARE_VIEWS_PCT": "2.53",
    "DELTA_SUBSCRIBERS_DOD": 0
  },
  {
    "DT_SNAPSHOT": "2026-05-07",
    "CANAL_ID": "UCwONybZQdULFV_ts2911Rqg",
    "CANAL_NOME": "Tiago Reis (Suno)",
    "CANAL_HANDLE": "@tiagoreis",
    "TIPO": "proprio",
    "BU": "Research,Asset",
    "SUBSCRIBERS": 816000,
    "VIEW_COUNT": 117283112,
    "VIDEO_COUNT": 4383,
    "SHARE_SUBSCRIBERS_PCT": "2.48",
    "SHARE_VIEWS_PCT": "3.02",
    "DELTA_SUBSCRIBERS_DOD": 0
  },
  {
    "DT_SNAPSHOT": "2026-05-07",
    "CANAL_ID": "UCxm0tptjIc76-i26EKQ9NpA",
    "CANAL_NOME": "InfoMoney",
    "CANAL_HANDLE": "@infomoney",
    "TIPO": "concorrente",
    "BU": "Redes Sociais",
    "SUBSCRIBERS": 734000,
    "VIEW_COUNT": 156964825,
    "VIDEO_COUNT": 18931,
    "SHARE_SUBSCRIBERS_PCT": "2.23",
    "SHARE_VIEWS_PCT": "4.04",
    "DELTA_SUBSCRIBERS_DOD": 0
  },
  {
    "DT_SNAPSHOT": "2026-05-07",
    "CANAL_ID": "UCWDeEIDAIi_oYKDiqwfGyRg",
    "CANAL_NOME": "Suno Research",
    "CANAL_HANDLE": "@gruposuno",
    "TIPO": "proprio",
    "BU": "Research,Asset,Redes Sociais",
    "SUBSCRIBERS": 518000,
    "VIEW_COUNT": 108232391,
    "VIDEO_COUNT": 4681,
    "SHARE_SUBSCRIBERS_PCT": "1.57",
    "SHARE_VIEWS_PCT": "2.79",
    "DELTA_SUBSCRIBERS_DOD": 0
  },
  {
    "DT_SNAPSHOT": "2026-05-07",
    "CANAL_ID": "UCf15n72n6pV0RK6-GOi1s1Q",
    "CANAL_NOME": "XP Investimentos",
    "CANAL_HANDLE": "@xp_oficial",
    "TIPO": "concorrente",
    "BU": "Redes Sociais",
    "SUBSCRIBERS": 487000,
    "VIEW_COUNT": 710272361,
    "VIDEO_COUNT": 3886,
    "SHARE_SUBSCRIBERS_PCT": "1.48",
    "SHARE_VIEWS_PCT": "18.30",
    "DELTA_SUBSCRIBERS_DOD": 0
  },
  {
    "DT_SNAPSHOT": "2026-05-07",
    "CANAL_ID": "UCSXdP8V4jRaw-8YMTpa6glw",
    "CANAL_NOME": "Suno Baroni",
    "CANAL_HANDLE": "@professorbaroni",
    "TIPO": "proprio",
    "BU": "Asset,Redes Sociais",
    "SUBSCRIBERS": 349000,
    "VIEW_COUNT": 42978063,
    "VIDEO_COUNT": 3253,
    "SHARE_SUBSCRIBERS_PCT": "1.06",
    "SHARE_VIEWS_PCT": "1.11",
    "DELTA_SUBSCRIBERS_DOD": 0
  },
  {
    "DT_SNAPSHOT": "2026-05-07",
    "CANAL_ID": "UCsU0E4F3RxVOSjWlIMieReA",
    "CANAL_NOME": "Nord Investimentos",
    "CANAL_HANDLE": "@nordinvestimentos",
    "TIPO": "concorrente",
    "BU": "Research,Redes Sociais",
    "SUBSCRIBERS": 273000,
    "VIEW_COUNT": 20470244,
    "VIDEO_COUNT": 1226,
    "SHARE_SUBSCRIBERS_PCT": "0.83",
    "SHARE_VIEWS_PCT": "0.53",
    "DELTA_SUBSCRIBERS_DOD": 0
  },
  {
    "DT_SNAPSHOT": "2026-05-07",
    "CANAL_ID": "UC74FvQ6GtdwRmENGymLjqNA",
    "CANAL_NOME": "Suno Noticias",
    "CANAL_HANDLE": "@sunonoticias",
    "TIPO": "proprio",
    "BU": "Redes Sociais",
    "SUBSCRIBERS": 73800,
    "VIEW_COUNT": 8691062,
    "VIDEO_COUNT": 3412,
    "SHARE_SUBSCRIBERS_PCT": "0.22",
    "SHARE_VIEWS_PCT": "0.22",
    "DELTA_SUBSCRIBERS_DOD": 0
  },
  {
    "DT_SNAPSHOT": "2026-05-07",
    "CANAL_ID": "UCAbPPg9IVIjzPBAE7uGgd-g",
    "CANAL_NOME": "Funds Explorer",
    "CANAL_HANDLE": "@fundsexplorer",
    "TIPO": "proprio",
    "BU": "Asset",
    "SUBSCRIBERS": 67400,
    "VIEW_COUNT": 2677535,
    "VIDEO_COUNT": 651,
    "SHARE_SUBSCRIBERS_PCT": "0.20",
    "SHARE_VIEWS_PCT": "0.07",
    "DELTA_SUBSCRIBERS_DOD": 0
  },
  {
    "DT_SNAPSHOT": "2026-05-07",
    "CANAL_ID": "UC7k3dDEfclcB07Deoy41D6g",
    "CANAL_NOME": "Status Invest",
    "CANAL_HANDLE": "@statusinvest",
    "TIPO": "proprio",
    "BU": "Asset",
    "SUBSCRIBERS": 61600,
    "VIEW_COUNT": 3115345,
    "VIDEO_COUNT": 642,
    "SHARE_SUBSCRIBERS_PCT": "0.19",
    "SHARE_VIEWS_PCT": "0.08",
    "DELTA_SUBSCRIBERS_DOD": 0
  },
  {
    "DT_SNAPSHOT": "2026-05-07",
    "CANAL_ID": "UCMP3ETiqEPs0RMjxH57O5DQ",
    "CANAL_NOME": "Suno Asset",
    "CANAL_HANDLE": "@sunoasset",
    "TIPO": "proprio",
    "BU": "Asset",
    "SUBSCRIBERS": 8770,
    "VIEW_COUNT": 4763667,
    "VIDEO_COUNT": 637,
    "SHARE_SUBSCRIBERS_PCT": "0.03",
    "SHARE_VIEWS_PCT": "0.12",
    "DELTA_SUBSCRIBERS_DOD": 0
  },
  {
    "DT_SNAPSHOT": "2026-05-06",
    "CANAL_ID": "UC8mDF5mWNGE-Kpfcvnn0bUg",
    "CANAL_NOME": "Me Poupe!",
    "CANAL_HANDLE": "@mepoupe",
    "TIPO": "concorrente",
    "BU": "Redes Sociais",
    "SUBSCRIBERS": 7730000,
    "VIEW_COUNT": 609868570,
    "VIDEO_COUNT": 2330,
    "SHARE_SUBSCRIBERS_PCT": "23.48",
    "SHARE_VIEWS_PCT": "15.72",
    "DELTA_SUBSCRIBERS_DOD": 0
  },
  {
    "DT_SNAPSHOT": "2026-05-06",
    "CANAL_ID": "UCT4nDeU5pv1XIGySbSK-GgA",
    "CANAL_NOME": "O Primo Rico",
    "CANAL_HANDLE": "@primorico",
    "TIPO": "concorrente",
    "BU": "Redes Sociais",
    "SUBSCRIBERS": 7600000,
    "VIEW_COUNT": 570504988,
    "VIDEO_COUNT": 1631,
    "SHARE_SUBSCRIBERS_PCT": "23.09",
    "SHARE_VIEWS_PCT": "14.70",
    "DELTA_SUBSCRIBERS_DOD": 10000
  },
  {
    "DT_SNAPSHOT": "2026-05-06",
    "CANAL_ID": "UCjt5Mt-yVu_R8LfuiLcd5KA",
    "CANAL_NOME": "Cafe com Ferri",
    "CANAL_HANDLE": "@podcastcafecomferri",
    "TIPO": "concorrente",
    "BU": "Redes Sociais",
    "SUBSCRIBERS": 6870000,
    "VIEW_COUNT": 155420555,
    "VIDEO_COUNT": 1260,
    "SHARE_SUBSCRIBERS_PCT": "20.87",
    "SHARE_VIEWS_PCT": "4.01",
    "DELTA_SUBSCRIBERS_DOD": 60000
  },
  {
    "DT_SNAPSHOT": "2026-05-06",
    "CANAL_ID": "UCCE-jo1GvBJqyj1b287h7jA",
    "CANAL_NOME": "Bruno Perini",
    "CANAL_HANDLE": "@brunoperini",
    "TIPO": "concorrente",
    "BU": "Redes Sociais",
    "SUBSCRIBERS": 2070000,
    "VIEW_COUNT": 471536500,
    "VIDEO_COUNT": 2350,
    "SHARE_SUBSCRIBERS_PCT": "6.29",
    "SHARE_VIEWS_PCT": "12.15",
    "DELTA_SUBSCRIBERS_DOD": 10000
  },
  {
    "DT_SNAPSHOT": "2026-05-06",
    "CANAL_ID": "UCM3vJxmuJJkk1r0yzFI9eZg",
    "CANAL_NOME": "Investidor Sardinha",
    "CANAL_HANDLE": "@investidorsardinha",
    "TIPO": "concorrente",
    "BU": "Asset,Redes Sociais",
    "SUBSCRIBERS": 1640000,
    "VIEW_COUNT": 305776873,
    "VIDEO_COUNT": 3094,
    "SHARE_SUBSCRIBERS_PCT": "4.98",
    "SHARE_VIEWS_PCT": "7.88",
    "DELTA_SUBSCRIBERS_DOD": 10000
  },
  {
    "DT_SNAPSHOT": "2026-05-06",
    "CANAL_ID": "UCrp0zmecZ3TNV8FSR-tjv7A",
    "CANAL_NOME": "Economista Sincero",
    "CANAL_HANDLE": "@economistasincero",
    "TIPO": "concorrente",
    "BU": "Redes Sociais",
    "SUBSCRIBERS": 1270000,
    "VIEW_COUNT": 274037267,
    "VIDEO_COUNT": 4219,
    "SHARE_SUBSCRIBERS_PCT": "3.86",
    "SHARE_VIEWS_PCT": "7.06",
    "DELTA_SUBSCRIBERS_DOD": 0
  },
  {
    "DT_SNAPSHOT": "2026-05-06",
    "CANAL_ID": "UCE5Uu3nZlVbTur6xwhdoKhg",
    "CANAL_NOME": "BTG Pactual",
    "CANAL_HANDLE": "@btgpactual",
    "TIPO": "concorrente",
    "BU": "Redes Sociais",
    "SUBSCRIBERS": 1260000,
    "VIEW_COUNT": 219286914,
    "VIDEO_COUNT": 2831,
    "SHARE_SUBSCRIBERS_PCT": "3.83",
    "SHARE_VIEWS_PCT": "5.65",
    "DELTA_SUBSCRIBERS_DOD": 10000
  },
  {
    "DT_SNAPSHOT": "2026-05-06",
    "CANAL_ID": "UCu79AeVqrq42vmSIp1OHyfA",
    "CANAL_NOME": "Empiricus",
    "CANAL_HANDLE": "@empiricus",
    "TIPO": "concorrente",
    "BU": "Research",
    "SUBSCRIBERS": 1090000,
    "VIEW_COUNT": 98316257,
    "VIDEO_COUNT": 2434,
    "SHARE_SUBSCRIBERS_PCT": "3.31",
    "SHARE_VIEWS_PCT": "2.53",
    "DELTA_SUBSCRIBERS_DOD": 10000
  },
  {
    "DT_SNAPSHOT": "2026-05-06",
    "CANAL_ID": "UCwONybZQdULFV_ts2911Rqg",
    "CANAL_NOME": "Tiago Reis (Suno)",
    "CANAL_HANDLE": "@tiagoreis",
    "TIPO": "proprio",
    "BU": "Research,Asset",
    "SUBSCRIBERS": 816000,
    "VIEW_COUNT": 117262213,
    "VIDEO_COUNT": 4383,
    "SHARE_SUBSCRIBERS_PCT": "2.48",
    "SHARE_VIEWS_PCT": "3.02",
    "DELTA_SUBSCRIBERS_DOD": 4000
  },
  {
    "DT_SNAPSHOT": "2026-05-06",
    "CANAL_ID": "UCxm0tptjIc76-i26EKQ9NpA",
    "CANAL_NOME": "InfoMoney",
    "CANAL_HANDLE": "@infomoney",
    "TIPO": "concorrente",
    "BU": "Redes Sociais",
    "SUBSCRIBERS": 734000,
    "VIEW_COUNT": 156892109,
    "VIDEO_COUNT": 18927,
    "SHARE_SUBSCRIBERS_PCT": "2.23",
    "SHARE_VIEWS_PCT": "4.04",
    "DELTA_SUBSCRIBERS_DOD": 3000
  },
  {
    "DT_SNAPSHOT": "2026-05-06",
    "CANAL_ID": "UCWDeEIDAIi_oYKDiqwfGyRg",
    "CANAL_NOME": "Suno Research",
    "CANAL_HANDLE": "@gruposuno",
    "TIPO": "proprio",
    "BU": "Research,Asset,Redes Sociais",
    "SUBSCRIBERS": 518000,
    "VIEW_COUNT": 108225904,
    "VIDEO_COUNT": 4679,
    "SHARE_SUBSCRIBERS_PCT": "1.57",
    "SHARE_VIEWS_PCT": "2.79",
    "DELTA_SUBSCRIBERS_DOD": 2000
  },
  {
    "DT_SNAPSHOT": "2026-05-06",
    "CANAL_ID": "UCf15n72n6pV0RK6-GOi1s1Q",
    "CANAL_NOME": "XP Investimentos",
    "CANAL_HANDLE": "@xp_oficial",
    "TIPO": "concorrente",
    "BU": "Redes Sociais",
    "SUBSCRIBERS": 487000,
    "VIEW_COUNT": 710265215,
    "VIDEO_COUNT": 3885,
    "SHARE_SUBSCRIBERS_PCT": "1.48",
    "SHARE_VIEWS_PCT": "18.31",
    "DELTA_SUBSCRIBERS_DOD": 0
  },
  {
    "DT_SNAPSHOT": "2026-05-06",
    "CANAL_ID": "UCSXdP8V4jRaw-8YMTpa6glw",
    "CANAL_NOME": "Suno Baroni",
    "CANAL_HANDLE": "@professorbaroni",
    "TIPO": "proprio",
    "BU": "Asset,Redes Sociais",
    "SUBSCRIBERS": 349000,
    "VIEW_COUNT": 42959180,
    "VIDEO_COUNT": 3252,
    "SHARE_SUBSCRIBERS_PCT": "1.06",
    "SHARE_VIEWS_PCT": "1.11",
    "DELTA_SUBSCRIBERS_DOD": 1000
  },
  {
    "DT_SNAPSHOT": "2026-05-06",
    "CANAL_ID": "UCsU0E4F3RxVOSjWlIMieReA",
    "CANAL_NOME": "Nord Investimentos",
    "CANAL_HANDLE": "@nordinvestimentos",
    "TIPO": "concorrente",
    "BU": "Research,Redes Sociais",
    "SUBSCRIBERS": 273000,
    "VIEW_COUNT": 20468032,
    "VIDEO_COUNT": 1226,
    "SHARE_SUBSCRIBERS_PCT": "0.83",
    "SHARE_VIEWS_PCT": "0.53",
    "DELTA_SUBSCRIBERS_DOD": 0
  },
  {
    "DT_SNAPSHOT": "2026-05-06",
    "CANAL_ID": "UC74FvQ6GtdwRmENGymLjqNA",
    "CANAL_NOME": "Suno Noticias",
    "CANAL_HANDLE": "@sunonoticias",
    "TIPO": "proprio",
    "BU": "Redes Sociais",
    "SUBSCRIBERS": 73800,
    "VIEW_COUNT": 8690841,
    "VIDEO_COUNT": 3412,
    "SHARE_SUBSCRIBERS_PCT": "0.22",
    "SHARE_VIEWS_PCT": "0.22",
    "DELTA_SUBSCRIBERS_DOD": 0
  },
  {
    "DT_SNAPSHOT": "2026-05-06",
    "CANAL_ID": "UCAbPPg9IVIjzPBAE7uGgd-g",
    "CANAL_NOME": "Funds Explorer",
    "CANAL_HANDLE": "@fundsexplorer",
    "TIPO": "proprio",
    "BU": "Asset",
    "SUBSCRIBERS": 67400,
    "VIEW_COUNT": 2672705,
    "VIDEO_COUNT": 651,
    "SHARE_SUBSCRIBERS_PCT": "0.20",
    "SHARE_VIEWS_PCT": "0.07",
    "DELTA_SUBSCRIBERS_DOD": 0
  },
  {
    "DT_SNAPSHOT": "2026-05-06",
    "CANAL_ID": "UC7k3dDEfclcB07Deoy41D6g",
    "CANAL_NOME": "Status Invest",
    "CANAL_HANDLE": "@statusinvest",
    "TIPO": "proprio",
    "BU": "Asset",
    "SUBSCRIBERS": 61600,
    "VIEW_COUNT": 3114884,
    "VIDEO_COUNT": 642,
    "SHARE_SUBSCRIBERS_PCT": "0.19",
    "SHARE_VIEWS_PCT": "0.08",
    "DELTA_SUBSCRIBERS_DOD": 1500
  },
  {
    "DT_SNAPSHOT": "2026-05-06",
    "CANAL_ID": "UCMP3ETiqEPs0RMjxH57O5DQ",
    "CANAL_NOME": "Suno Asset",
    "CANAL_HANDLE": "@sunoasset",
    "TIPO": "proprio",
    "BU": "Asset",
    "SUBSCRIBERS": 8770,
    "VIEW_COUNT": 4762578,
    "VIDEO_COUNT": 637,
    "SHARE_SUBSCRIBERS_PCT": "0.03",
    "SHARE_VIEWS_PCT": "0.12",
    "DELTA_SUBSCRIBERS_DOD": 70
  },
  {
    "DT_SNAPSHOT": "2026-04-24",
    "CANAL_ID": "UC8mDF5mWNGE-Kpfcvnn0bUg",
    "CANAL_NOME": "Me Poupe!",
    "CANAL_HANDLE": "@mepoupe",
    "TIPO": "concorrente",
    "BU": "Redes Sociais",
    "SUBSCRIBERS": 7730000,
    "VIEW_COUNT": 608374264,
    "VIDEO_COUNT": 2298,
    "SHARE_SUBSCRIBERS_PCT": "23.57",
    "SHARE_VIEWS_PCT": "15.76",
    "DELTA_SUBSCRIBERS_DOD": null
  },
  {
    "DT_SNAPSHOT": "2026-04-24",
    "CANAL_ID": "UCT4nDeU5pv1XIGySbSK-GgA",
    "CANAL_NOME": "O Primo Rico",
    "CANAL_HANDLE": "@primorico",
    "TIPO": "concorrente",
    "BU": "Redes Sociais",
    "SUBSCRIBERS": 7590000,
    "VIEW_COUNT": 567843248,
    "VIDEO_COUNT": 1619,
    "SHARE_SUBSCRIBERS_PCT": "23.14",
    "SHARE_VIEWS_PCT": "14.71",
    "DELTA_SUBSCRIBERS_DOD": null
  },
  {
    "DT_SNAPSHOT": "2026-04-24",
    "CANAL_ID": "UCjt5Mt-yVu_R8LfuiLcd5KA",
    "CANAL_NOME": "Cafe com Ferri",
    "CANAL_HANDLE": "@podcastcafecomferri",
    "TIPO": "concorrente",
    "BU": "Redes Sociais",
    "SUBSCRIBERS": 6810000,
    "VIEW_COUNT": 151321282,
    "VIDEO_COUNT": 1248,
    "SHARE_SUBSCRIBERS_PCT": "20.76",
    "SHARE_VIEWS_PCT": "3.92",
    "DELTA_SUBSCRIBERS_DOD": null
  },
  {
    "DT_SNAPSHOT": "2026-04-24",
    "CANAL_ID": "UCCE-jo1GvBJqyj1b287h7jA",
    "CANAL_NOME": "Bruno Perini",
    "CANAL_HANDLE": "@brunoperini",
    "TIPO": "concorrente",
    "BU": "Redes Sociais",
    "SUBSCRIBERS": 2060000,
    "VIEW_COUNT": 470170918,
    "VIDEO_COUNT": 2339,
    "SHARE_SUBSCRIBERS_PCT": "6.28",
    "SHARE_VIEWS_PCT": "12.18",
    "DELTA_SUBSCRIBERS_DOD": null
  },
  {
    "DT_SNAPSHOT": "2026-04-24",
    "CANAL_ID": "UCM3vJxmuJJkk1r0yzFI9eZg",
    "CANAL_NOME": "Investidor Sardinha",
    "CANAL_HANDLE": "@investidorsardinha",
    "TIPO": "concorrente",
    "BU": "Asset,Redes Sociais",
    "SUBSCRIBERS": 1630000,
    "VIEW_COUNT": 302825782,
    "VIDEO_COUNT": 3081,
    "SHARE_SUBSCRIBERS_PCT": "4.97",
    "SHARE_VIEWS_PCT": "7.84",
    "DELTA_SUBSCRIBERS_DOD": null
  },
  {
    "DT_SNAPSHOT": "2026-04-24",
    "CANAL_ID": "UCrp0zmecZ3TNV8FSR-tjv7A",
    "CANAL_NOME": "Economista Sincero",
    "CANAL_HANDLE": "@economistasincero",
    "TIPO": "concorrente",
    "BU": "Redes Sociais",
    "SUBSCRIBERS": 1270000,
    "VIEW_COUNT": 273084806,
    "VIDEO_COUNT": 4184,
    "SHARE_SUBSCRIBERS_PCT": "3.87",
    "SHARE_VIEWS_PCT": "7.07",
    "DELTA_SUBSCRIBERS_DOD": null
  },
  {
    "DT_SNAPSHOT": "2026-04-24",
    "CANAL_ID": "UCE5Uu3nZlVbTur6xwhdoKhg",
    "CANAL_NOME": "BTG Pactual",
    "CANAL_HANDLE": "@btgpactual",
    "TIPO": "concorrente",
    "BU": "Redes Sociais",
    "SUBSCRIBERS": 1250000,
    "VIEW_COUNT": 217495258,
    "VIDEO_COUNT": 2816,
    "SHARE_SUBSCRIBERS_PCT": "3.81",
    "SHARE_VIEWS_PCT": "5.63",
    "DELTA_SUBSCRIBERS_DOD": null
  },
  {
    "DT_SNAPSHOT": "2026-04-24",
    "CANAL_ID": "UCu79AeVqrq42vmSIp1OHyfA",
    "CANAL_NOME": "Empiricus",
    "CANAL_HANDLE": "@empiricus",
    "TIPO": "concorrente",
    "BU": "Research",
    "SUBSCRIBERS": 1080000,
    "VIEW_COUNT": 98238870,
    "VIDEO_COUNT": 2414,
    "SHARE_SUBSCRIBERS_PCT": "3.29",
    "SHARE_VIEWS_PCT": "2.54",
    "DELTA_SUBSCRIBERS_DOD": null
  },
  {
    "DT_SNAPSHOT": "2026-04-24",
    "CANAL_ID": "UCwONybZQdULFV_ts2911Rqg",
    "CANAL_NOME": "Tiago Reis (Suno)",
    "CANAL_HANDLE": "@tiagoreis",
    "TIPO": "proprio",
    "BU": "Research,Asset",
    "SUBSCRIBERS": 812000,
    "VIEW_COUNT": 116803226,
    "VIDEO_COUNT": 4380,
    "SHARE_SUBSCRIBERS_PCT": "2.48",
    "SHARE_VIEWS_PCT": "3.03",
    "DELTA_SUBSCRIBERS_DOD": null
  },
  {
    "DT_SNAPSHOT": "2026-04-24",
    "CANAL_ID": "UCxm0tptjIc76-i26EKQ9NpA",
    "CANAL_NOME": "InfoMoney",
    "CANAL_HANDLE": "@infomoney",
    "TIPO": "concorrente",
    "BU": "Redes Sociais",
    "SUBSCRIBERS": 731000,
    "VIEW_COUNT": 154203666,
    "VIDEO_COUNT": 18647,
    "SHARE_SUBSCRIBERS_PCT": "2.23",
    "SHARE_VIEWS_PCT": "3.99",
    "DELTA_SUBSCRIBERS_DOD": null
  },
  {
    "DT_SNAPSHOT": "2026-04-24",
    "CANAL_ID": "UCWDeEIDAIi_oYKDiqwfGyRg",
    "CANAL_NOME": "Suno Research",
    "CANAL_HANDLE": "@gruposuno",
    "TIPO": "proprio",
    "BU": "Research,Asset,Redes Sociais",
    "SUBSCRIBERS": 516000,
    "VIEW_COUNT": 107909022,
    "VIDEO_COUNT": 4664,
    "SHARE_SUBSCRIBERS_PCT": "1.57",
    "SHARE_VIEWS_PCT": "2.80",
    "DELTA_SUBSCRIBERS_DOD": null
  },
  {
    "DT_SNAPSHOT": "2026-04-24",
    "CANAL_ID": "UCf15n72n6pV0RK6-GOi1s1Q",
    "CANAL_NOME": "XP Investimentos",
    "CANAL_HANDLE": "@xp_oficial",
    "TIPO": "concorrente",
    "BU": "Redes Sociais",
    "SUBSCRIBERS": 487000,
    "VIEW_COUNT": 709823364,
    "VIDEO_COUNT": 3865,
    "SHARE_SUBSCRIBERS_PCT": "1.48",
    "SHARE_VIEWS_PCT": "18.39",
    "DELTA_SUBSCRIBERS_DOD": null
  },
  {
    "DT_SNAPSHOT": "2026-04-24",
    "CANAL_ID": "UCSXdP8V4jRaw-8YMTpa6glw",
    "CANAL_NOME": "Suno Baroni",
    "CANAL_HANDLE": "@professorbaroni",
    "TIPO": "proprio",
    "BU": "Asset,Redes Sociais",
    "SUBSCRIBERS": 348000,
    "VIEW_COUNT": 42745703,
    "VIDEO_COUNT": 3225,
    "SHARE_SUBSCRIBERS_PCT": "1.06",
    "SHARE_VIEWS_PCT": "1.11",
    "DELTA_SUBSCRIBERS_DOD": null
  },
  {
    "DT_SNAPSHOT": "2026-04-24",
    "CANAL_ID": "UCsU0E4F3RxVOSjWlIMieReA",
    "CANAL_NOME": "Nord Investimentos",
    "CANAL_HANDLE": "@nordinvestimentos",
    "TIPO": "concorrente",
    "BU": "Research,Redes Sociais",
    "SUBSCRIBERS": 273000,
    "VIEW_COUNT": 20399983,
    "VIDEO_COUNT": 1223,
    "SHARE_SUBSCRIBERS_PCT": "0.83",
    "SHARE_VIEWS_PCT": "0.53",
    "DELTA_SUBSCRIBERS_DOD": null
  },
  {
    "DT_SNAPSHOT": "2026-04-24",
    "CANAL_ID": "UC74FvQ6GtdwRmENGymLjqNA",
    "CANAL_NOME": "Suno Noticias",
    "CANAL_HANDLE": "@sunonoticias",
    "TIPO": "proprio",
    "BU": "Redes Sociais",
    "SUBSCRIBERS": 73800,
    "VIEW_COUNT": 8686826,
    "VIDEO_COUNT": 3412,
    "SHARE_SUBSCRIBERS_PCT": "0.23",
    "SHARE_VIEWS_PCT": "0.23",
    "DELTA_SUBSCRIBERS_DOD": null
  },
  {
    "DT_SNAPSHOT": "2026-04-24",
    "CANAL_ID": "UCAbPPg9IVIjzPBAE7uGgd-g",
    "CANAL_NOME": "Funds Explorer",
    "CANAL_HANDLE": "@fundsexplorer",
    "TIPO": "proprio",
    "BU": "Asset",
    "SUBSCRIBERS": 67400,
    "VIEW_COUNT": 2668383,
    "VIDEO_COUNT": 647,
    "SHARE_SUBSCRIBERS_PCT": "0.21",
    "SHARE_VIEWS_PCT": "0.07",
    "DELTA_SUBSCRIBERS_DOD": null
  },
  {
    "DT_SNAPSHOT": "2026-04-24",
    "CANAL_ID": "UC7k3dDEfclcB07Deoy41D6g",
    "CANAL_NOME": "Status Invest",
    "CANAL_HANDLE": "@statusinvest",
    "TIPO": "proprio",
    "BU": "Asset",
    "SUBSCRIBERS": 60100,
    "VIEW_COUNT": 3031392,
    "VIDEO_COUNT": 639,
    "SHARE_SUBSCRIBERS_PCT": "0.18",
    "SHARE_VIEWS_PCT": "0.08",
    "DELTA_SUBSCRIBERS_DOD": null
  },
  {
    "DT_SNAPSHOT": "2026-04-24",
    "CANAL_ID": "UCMP3ETiqEPs0RMjxH57O5DQ",
    "CANAL_NOME": "Suno Asset",
    "CANAL_HANDLE": "@sunoasset",
    "TIPO": "proprio",
    "BU": "Asset",
    "SUBSCRIBERS": 8700,
    "VIEW_COUNT": 4744499,
    "VIDEO_COUNT": 632,
    "SHARE_SUBSCRIBERS_PCT": "0.03",
    "SHARE_VIEWS_PCT": "0.12",
    "DELTA_SUBSCRIBERS_DOD": null
  }
]